{
"meta":{"test_sets":[],"test_metrics":[],"learn_metrics":[{"best_value":"Min","name":"RMSE"}],"launch_mode":"Train","parameters":"","iteration_count":1000,"learn_sets":["learn"],"name":"experiment"},
"iterations":[
{"learn":[3.186901991],"iteration":0,"passed_time":0.07308445885,"remaining_time":73.01137439},
{"learn":[3.162850301],"iteration":1,"passed_time":0.07346419389,"remaining_time":36.65863275},
{"learn":[3.140012241],"iteration":2,"passed_time":0.0738708171,"remaining_time":24.54973488},
{"learn":[3.11516858],"iteration":3,"passed_time":0.07432348195,"remaining_time":18.506547},
{"learn":[3.094746098],"iteration":4,"passed_time":0.07466761809,"remaining_time":14.858856},
{"learn":[3.071990707],"iteration":5,"passed_time":0.07507246747,"remaining_time":12.43700544},
{"learn":[3.050169226],"iteration":6,"passed_time":0.0754729697,"remaining_time":10.70637984},
{"learn":[3.027975887],"iteration":7,"passed_time":0.07588595211,"remaining_time":9.409858061},
{"learn":[3.010987638],"iteration":8,"passed_time":0.07634075887,"remaining_time":8.405965782},
{"learn":[2.994216807],"iteration":9,"passed_time":0.07679935664,"remaining_time":7.603136308},
{"learn":[2.972016271],"iteration":10,"passed_time":0.07719470002,"remaining_time":6.940505302},
{"learn":[2.961227393],"iteration":11,"passed_time":0.07740627035,"remaining_time":6.373116259},
{"learn":[2.945628185],"iteration":12,"passed_time":0.07774323336,"remaining_time":5.902505487},
{"learn":[2.930868689],"iteration":13,"passed_time":0.07808926582,"remaining_time":5.499715436},
{"learn":[2.916685752],"iteration":14,"passed_time":0.07836279634,"remaining_time":5.145823626},
{"learn":[2.901324223],"iteration":15,"passed_time":0.07871100222,"remaining_time":4.840726636},
{"learn":[2.887165306],"iteration":16,"passed_time":0.07904564651,"remaining_time":4.570698266},
{"learn":[2.874175164],"iteration":17,"passed_time":0.07939124371,"remaining_time":4.331233407},
{"learn":[2.860855266],"iteration":18,"passed_time":0.07980281972,"remaining_time":4.120345586},
{"learn":[2.852290534],"iteration":19,"passed_time":0.08007941893,"remaining_time":3.923891527},
{"learn":[2.838580236],"iteration":20,"passed_time":0.08047321703,"remaining_time":3.751584737},
{"learn":[2.828401683],"iteration":21,"passed_time":0.08088032662,"remaining_time":3.595498156},
{"learn":[2.815452678],"iteration":22,"passed_time":0.08131630525,"remaining_time":3.454175227},
{"learn":[2.80592502],"iteration":23,"passed_time":0.08173700857,"remaining_time":3.323971682},
{"learn":[2.796796436],"iteration":24,"passed_time":0.08220542996,"remaining_time":3.206011768},
{"learn":[2.785961555],"iteration":25,"passed_time":0.08263109314,"remaining_time":3.095487874},
{"learn":[2.777657513],"iteration":26,"passed_time":0.08300646623,"remaining_time":2.991307098},
{"learn":[2.77114534],"iteration":27,"passed_time":0.08337513649,"remaining_time":2.89430831},
{"learn":[2.762725886],"iteration":28,"passed_time":0.08380136545,"remaining_time":2.805900891},
{"learn":[2.758048469],"iteration":29,"passed_time":0.08415409754,"remaining_time":2.720982487},
{"learn":[2.748523559],"iteration":30,"passed_time":0.08450045403,"remaining_time":2.641320644},
{"learn":[2.738990357],"iteration":31,"passed_time":0.08483866754,"remaining_time":2.566369693},
{"learn":[2.732167288],"iteration":32,"passed_time":0.08518858714,"remaining_time":2.49628375},
{"learn":[2.725815903],"iteration":33,"passed_time":0.08552612942,"remaining_time":2.429948265},
{"learn":[2.718763306],"iteration":34,"passed_time":0.08595760982,"remaining_time":2.369974099},
{"learn":[2.71294898],"iteration":35,"passed_time":0.08633148039,"remaining_time":2.311765197},
{"learn":[2.708426689],"iteration":36,"passed_time":0.08658227474,"remaining_time":2.253479205},
{"learn":[2.699272491],"iteration":37,"passed_time":0.08699334219,"remaining_time":2.202305137},
{"learn":[2.693051489],"iteration":38,"passed_time":0.08741883822,"remaining_time":2.154089834},
{"learn":[2.68768363],"iteration":39,"passed_time":0.08789540646,"remaining_time":2.109489755},
{"learn":[2.682495349],"iteration":40,"passed_time":0.08836184377,"remaining_time":2.066805077},
{"learn":[2.679811255],"iteration":41,"passed_time":0.08860571123,"remaining_time":2.02105408},
{"learn":[2.673817004],"iteration":42,"passed_time":0.08902674887,"remaining_time":1.98136276},
{"learn":[2.667840953],"iteration":43,"passed_time":0.08935990704,"remaining_time":1.941547071},
{"learn":[2.663380338],"iteration":44,"passed_time":0.08969359369,"remaining_time":1.903497377},
{"learn":[2.659153599],"iteration":45,"passed_time":0.09004353419,"remaining_time":1.8674246},
{"learn":[2.653230149],"iteration":46,"passed_time":0.09038383206,"remaining_time":1.832676425},
{"learn":[2.649383073],"iteration":47,"passed_time":0.09073803324,"remaining_time":1.799637659},
{"learn":[2.640702289],"iteration":48,"passed_time":0.09107666464,"remaining_time":1.767630777},
{"learn":[2.636120468],"iteration":49,"passed_time":0.09145004305,"remaining_time":1.737550818},
{"learn":[2.634851964],"iteration":50,"passed_time":0.09160683919,"remaining_time":1.704605694},
{"learn":[2.63128285],"iteration":51,"passed_time":0.09203387985,"remaining_time":1.677848425},
{"learn":[2.627036616],"iteration":52,"passed_time":0.09243033324,"remaining_time":1.651538218},
{"learn":[2.623761867],"iteration":53,"passed_time":0.09353222637,"remaining_time":1.63854604},
{"learn":[2.619772646],"iteration":54,"passed_time":0.0940095269,"remaining_time":1.615254599},
{"learn":[2.618750511],"iteration":55,"passed_time":0.09421788549,"remaining_time":1.588244355},
{"learn":[2.613805473],"iteration":56,"passed_time":0.09469811038,"remaining_time":1.566672247},
{"learn":[2.608143235],"iteration":57,"passed_time":0.09510624608,"remaining_time":1.544656617},
{"learn":[2.604734927],"iteration":58,"passed_time":0.09550130303,"remaining_time":1.52316485},
{"learn":[2.601545975],"iteration":59,"passed_time":0.09585762201,"remaining_time":1.501769412},
{"learn":[2.596823629],"iteration":60,"passed_time":0.0962776194,"remaining_time":1.48204401},
{"learn":[2.593437271],"iteration":61,"passed_time":0.09664425061,"remaining_time":1.462133985},
{"learn":[2.588465578],"iteration":62,"passed_time":0.09700171882,"remaining_time":1.442708104},
{"learn":[2.585930353],"iteration":63,"passed_time":0.09733545755,"remaining_time":1.423531067},
{"learn":[2.582747572],"iteration":64,"passed_time":0.09770999676,"remaining_time":1.405520723},
{"learn":[2.578151886],"iteration":65,"passed_time":0.09812171454,"remaining_time":1.38857093},
{"learn":[2.57433566],"iteration":66,"passed_time":0.09855005198,"remaining_time":1.372346246},
{"learn":[2.571367085],"iteration":67,"passed_time":0.09897454246,"remaining_time":1.356533435},
{"learn":[2.565314094],"iteration":68,"passed_time":0.09938936782,"remaining_time":1.341036253},
{"learn":[2.559215128],"iteration":69,"passed_time":0.09981783192,"remaining_time":1.326151196},
{"learn":[2.556167745],"iteration":70,"passed_time":0.1002550864,"remaining_time":1.311788385},
{"learn":[2.550843913],"iteration":71,"passed_time":0.1006646732,"remaining_time":1.297455788},
{"learn":[2.545691019],"iteration":72,"passed_time":0.1010894472,"remaining_time":1.283697501},
{"learn":[2.539489916],"iteration":73,"passed_time":0.1014398609,"remaining_time":1.269369071},
{"learn":[2.534608949],"iteration":74,"passed_time":0.1017707898,"remaining_time":1.255173074},
{"learn":[2.527854999],"iteration":75,"passed_time":0.1021106196,"remaining_time":1.241450164},
{"learn":[2.522920025],"iteration":76,"passed_time":0.1024665059,"remaining_time":1.228267336},
{"learn":[2.520298882],"iteration":77,"passed_time":0.10279971,"remaining_time":1.21514529},
{"learn":[2.518151238],"iteration":78,"passed_time":0.1031352332,"remaining_time":1.202374047},
{"learn":[2.513937937],"iteration":79,"passed_time":0.1034678844,"remaining_time":1.18988067},
{"learn":[2.510773911],"iteration":80,"passed_time":0.1037929118,"remaining_time":1.177601061},
{"learn":[2.507697028],"iteration":81,"passed_time":0.1041804092,"remaining_time":1.166312386},
{"learn":[2.50531692],"iteration":82,"passed_time":0.1046063469,"remaining_time":1.155711086},
{"learn":[2.501718099],"iteration":83,"passed_time":0.1050041906,"remaining_time":1.145045698},
{"learn":[2.499505916],"iteration":84,"passed_time":0.1054376049,"remaining_time":1.135004806},
{"learn":[2.498705626],"iteration":85,"passed_time":0.1058491977,"remaining_time":1.124955426},
{"learn":[2.497226643],"iteration":86,"passed_time":0.1063048769,"remaining_time":1.11559026},
{"learn":[2.493773669],"iteration":87,"passed_time":0.1067628777,"remaining_time":1.106451642},
{"learn":[2.488841296],"iteration":88,"passed_time":0.1072365216,"remaining_time":1.097668215},
{"learn":[2.487133338],"iteration":89,"passed_time":0.1076534606,"remaining_time":1.088496101},
{"learn":[2.483287741],"iteration":90,"passed_time":0.1080483658,"remaining_time":1.079296313},
{"learn":[2.483003809],"iteration":91,"passed_time":0.1082347318,"remaining_time":1.068229744},
{"learn":[2.481180593],"iteration":92,"passed_time":0.1086054282,"remaining_time":1.059194875},
{"learn":[2.476735349],"iteration":93,"passed_time":0.1089591346,"remaining_time":1.050180596},
{"learn":[2.474119931],"iteration":94,"passed_time":0.1092935102,"remaining_time":1.041164492},
{"learn":[2.473013801],"iteration":95,"passed_time":0.1096113895,"remaining_time":1.032173918},
{"learn":[2.470693105],"iteration":96,"passed_time":0.1099485817,"remaining_time":1.023541951},
{"learn":[2.470244225],"iteration":97,"passed_time":0.1102132212,"remaining_time":1.014411485},
{"learn":[2.468398196],"iteration":98,"passed_time":0.1106169747,"remaining_time":1.006726204},
{"learn":[2.468084916],"iteration":99,"passed_time":0.1108848227,"remaining_time":0.9979634044},
{"learn":[2.4644401],"iteration":100,"passed_time":0.1113030498,"remaining_time":0.9907073442},
{"learn":[2.462614293],"iteration":101,"passed_time":0.1116955386,"remaining_time":0.9833587612},
{"learn":[2.461015492],"iteration":102,"passed_time":0.1120752039,"remaining_time":0.9760335714},
{"learn":[2.458342328],"iteration":103,"passed_time":0.112452417,"remaining_time":0.9688208234},
{"learn":[2.456217288],"iteration":104,"passed_time":0.1128421743,"remaining_time":0.9618452},
{"learn":[2.453619349],"iteration":105,"passed_time":0.1132871575,"remaining_time":0.955459611},
{"learn":[2.45145746],"iteration":106,"passed_time":0.1136394433,"remaining_time":0.9484114291},
{"learn":[2.448199263],"iteration":107,"passed_time":0.1140248561,"remaining_time":0.9417608483},
{"learn":[2.446878096],"iteration":108,"passed_time":0.1144778536,"remaining_time":0.9357776843},
{"learn":[2.446420386],"iteration":109,"passed_time":0.1147447382,"remaining_time":0.9283892455},
{"learn":[2.445792027],"iteration":110,"passed_time":0.1151426761,"remaining_time":0.9221787304},
{"learn":[2.444235673],"iteration":111,"passed_time":0.1154912073,"remaining_time":0.9156802866},
{"learn":[2.440617895],"iteration":112,"passed_time":0.1158331234,"remaining_time":0.9092387654},
{"learn":[2.436664237],"iteration":113,"passed_time":0.1161626831,"remaining_time":0.9028082216},
{"learn":[2.43545325],"iteration":114,"passed_time":0.1165227729,"remaining_time":0.8967187305},
{"learn":[2.432483348],"iteration":115,"passed_time":0.1169429943,"remaining_time":0.8911862672},
{"learn":[2.431481163],"iteration":116,"passed_time":0.117389165,"remaining_time":0.8859370314},
{"learn":[2.42793312],"iteration":117,"passed_time":0.1178974096,"remaining_time":0.8812331802},
{"learn":[2.427907582],"iteration":118,"passed_time":0.1181237132,"remaining_time":0.8745125325},
{"learn":[2.426263423],"iteration":119,"passed_time":0.1185222176,"remaining_time":0.8691629289},
{"learn":[2.42301413],"iteration":120,"passed_time":0.1190110824,"remaining_time":0.8645515824},
{"learn":[2.42158105],"iteration":121,"passed_time":0.1194624322,"remaining_time":0.8597378316},
{"learn":[2.420502581],"iteration":122,"passed_time":0.1197996874,"remaining_time":0.854181511},
{"learn":[2.42029887],"iteration":123,"passed_time":0.1200353202,"remaining_time":0.8479914559},
{"learn":[2.418355343],"iteration":124,"passed_time":0.1203952322,"remaining_time":0.8427666256},
{"learn":[2.417043893],"iteration":125,"passed_time":0.1207550474,"remaining_time":0.8376183449},
{"learn":[2.416043178],"iteration":126,"passed_time":0.1210856426,"remaining_time":0.8323446139},
{"learn":[2.413571764],"iteration":127,"passed_time":0.1214368741,"remaining_time":0.8272887046},
{"learn":[2.410795082],"iteration":128,"passed_time":0.1217829888,"remaining_time":0.8222711881},
{"learn":[2.408600368],"iteration":129,"passed_time":0.1221047289,"remaining_time":0.8171624167},
{"learn":[2.408590529],"iteration":130,"passed_time":0.1222504812,"remaining_time":0.8109592988},
{"learn":[2.404949209],"iteration":131,"passed_time":0.122621764,"remaining_time":0.8063309934},
{"learn":[2.403758395],"iteration":132,"passed_time":0.1230604857,"remaining_time":0.8022063238},
{"learn":[2.401859947],"iteration":133,"passed_time":0.1234839024,"remaining_time":0.7980377576},
{"learn":[2.398204656],"iteration":134,"passed_time":0.1239413764,"remaining_time":0.7941428932},
{"learn":[2.395780687],"iteration":135,"passed_time":0.1243567357,"remaining_time":0.7900310268},
{"learn":[2.395746362],"iteration":136,"passed_time":0.1245712638,"remaining_time":0.7847080341},
{"learn":[2.394469534],"iteration":137,"passed_time":0.1249704455,"remaining_time":0.7806124927},
{"learn":[2.390921271],"iteration":138,"passed_time":0.1253685814,"remaining_time":0.7765636589},
{"learn":[2.389474668],"iteration":139,"passed_time":0.125732838,"remaining_time":0.7723588618},
{"learn":[2.387470282],"iteration":140,"passed_time":0.1260718529,"remaining_time":0.7680547632},
{"learn":[2.384865449],"iteration":141,"passed_time":0.1264292758,"remaining_time":0.7639177366},
{"learn":[2.384157045],"iteration":142,"passed_time":0.1267591733,"remaining_time":0.7596686121},
{"learn":[2.382925763],"iteration":143,"passed_time":0.1271010354,"remaining_time":0.755545044},
{"learn":[2.380865096],"iteration":144,"passed_time":0.1274506702,"remaining_time":0.7515194692},
{"learn":[2.378146655],"iteration":145,"passed_time":0.1278031561,"remaining_time":0.7475609265},
{"learn":[2.376678706],"iteration":146,"passed_time":0.128202988,"remaining_time":0.7439261823},
{"learn":[2.374328069],"iteration":147,"passed_time":0.1285653586,"remaining_time":0.7401194966},
{"learn":[2.37316354],"iteration":148,"passed_time":0.1289000295,"remaining_time":0.7362008399},
{"learn":[2.372479996],"iteration":149,"passed_time":0.1292735844,"remaining_time":0.7325503118},
{"learn":[2.368378274],"iteration":150,"passed_time":0.1296513769,"remaining_time":0.7289670129},
{"learn":[2.367476482],"iteration":151,"passed_time":0.1301350305,"remaining_time":0.7260164858},
{"learn":[2.363991851],"iteration":152,"passed_time":0.130540427,"remaining_time":0.7226649782},
{"learn":[2.362726285],"iteration":153,"passed_time":0.1310201112,"remaining_time":0.7197598315},
{"learn":[2.360482847],"iteration":154,"passed_time":0.1314460405,"remaining_time":0.7165929306},
{"learn":[2.359482868],"iteration":155,"passed_time":0.1318773454,"remaining_time":0.7134902533},
{"learn":[2.356387067],"iteration":156,"passed_time":0.1323086596,"remaining_time":0.7104216563},
{"learn":[2.349797924],"iteration":157,"passed_time":0.132742072,"remaining_time":0.7073976241},
{"learn":[2.348134183],"iteration":158,"passed_time":0.1331254055,"remaining_time":0.7041412957},
{"learn":[2.345398604],"iteration":159,"passed_time":0.13349889,"remaining_time":0.7008691724},
{"learn":[2.343789288],"iteration":160,"passed_time":0.1339005639,"remaining_time":0.6977799574},
{"learn":[2.342670304],"iteration":161,"passed_time":0.1342654853,"remaining_time":0.6945338066},
{"learn":[2.33835966],"iteration":162,"passed_time":0.1346140489,"remaining_time":0.6912390121},
{"learn":[2.337453156],"iteration":163,"passed_time":0.1349824283,"remaining_time":0.6880811588},
{"learn":[2.33698741],"iteration":164,"passed_time":0.1353619743,"remaining_time":0.6850136275},
{"learn":[2.335340241],"iteration":165,"passed_time":0.1357547852,"remaining_time":0.6820451255},
{"learn":[2.329484933],"iteration":166,"passed_time":0.1362062288,"remaining_time":0.6793999316},
{"learn":[2.328670695],"iteration":167,"passed_time":0.1366280164,"remaining_time":0.676633986},
{"learn":[2.327564233],"iteration":168,"passed_time":0.1370688585,"remaining_time":0.6739894756},
{"learn":[2.326200597],"iteration":169,"passed_time":0.1374373191,"remaining_time":0.6710174992},
{"learn":[2.321898433],"iteration":170,"passed_time":0.1378488816,"remaining_time":0.668284929},
{"learn":[2.320587938],"iteration":171,"passed_time":0.1382444156,"remaining_time":0.6655021868},
{"learn":[2.318758791],"iteration":172,"passed_time":0.138696749,"remaining_time":0.6630185633},
{"learn":[2.316926876],"iteration":173,"passed_time":0.1391299001,"remaining_time":0.6604672268},
{"learn":[2.315789342],"iteration":174,"passed_time":0.1395589463,"remaining_time":0.6579207471},
{"learn":[2.314134943],"iteration":175,"passed_time":0.1399391282,"remaining_time":0.6551695548},
{"learn":[2.311274408],"iteration":176,"passed_time":0.1402779316,"remaining_time":0.6522527554},
{"learn":[2.309247139],"iteration":177,"passed_time":0.1405957746,"remaining_time":0.6492681276},
{"learn":[2.305864456],"iteration":178,"passed_time":0.1409905641,"remaining_time":0.6466662185},
{"learn":[2.304980292],"iteration":179,"passed_time":0.141343364,"remaining_time":0.6438975471},
{"learn":[2.300727888],"iteration":180,"passed_time":0.1417277644,"remaining_time":0.6412985584},
{"learn":[2.297254642],"iteration":181,"passed_time":0.1421237623,"remaining_time":0.6387760306},
{"learn":[2.295661319],"iteration":182,"passed_time":0.1425636033,"remaining_time":0.6364724805},
{"learn":[2.294141583],"iteration":183,"passed_time":0.1430179899,"remaining_time":0.6342536945},
{"learn":[2.292609435],"iteration":184,"passed_time":0.1434692561,"remaining_time":0.6320402363},
{"learn":[2.288163433],"iteration":185,"passed_time":0.1438687611,"remaining_time":0.629619202},
{"learn":[2.28559636],"iteration":186,"passed_time":0.1442314075,"remaining_time":0.6270595416},
{"learn":[2.284904658],"iteration":187,"passed_time":0.1446130157,"remaining_time":0.6246051529},
{"learn":[2.28393384],"iteration":188,"passed_time":0.1450823999,"remaining_time":0.6225493454},
{"learn":[2.281780545],"iteration":189,"passed_time":0.1454596693,"remaining_time":0.6201175374},
{"learn":[2.279162781],"iteration":190,"passed_time":0.1458147975,"remaining_time":0.6176134618},
{"learn":[2.277344688],"iteration":191,"passed_time":0.1461772324,"remaining_time":0.6151625195},
{"learn":[2.275731706],"iteration":192,"passed_time":0.146539952,"remaining_time":0.6127344107},
{"learn":[2.273984657],"iteration":193,"passed_time":0.1469079539,"remaining_time":0.6103495406},
{"learn":[2.271179459],"iteration":194,"passed_time":0.1472655681,"remaining_time":0.6079424734},
{"learn":[2.269768964],"iteration":195,"passed_time":0.1476172252,"remaining_time":0.605531883},
{"learn":[2.267754143],"iteration":196,"passed_time":0.1480213793,"remaining_time":0.6033561804},
{"learn":[2.263571384],"iteration":197,"passed_time":0.1484828249,"remaining_time":0.6014304321},
{"learn":[2.263235073],"iteration":198,"passed_time":0.1489391972,"remaining_time":0.5994989795},
{"learn":[2.259985128],"iteration":199,"passed_time":0.1493799499,"remaining_time":0.5975197994},
{"learn":[2.259362138],"iteration":200,"passed_time":0.1497829447,"remaining_time":0.5954058349},
{"learn":[2.259091358],"iteration":201,"passed_time":0.150132106,"remaining_time":0.5930961414},
{"learn":[2.25742474],"iteration":202,"passed_time":0.1505365998,"remaining_time":0.5910230052},
{"learn":[2.255984521],"iteration":203,"passed_time":0.1508926835,"remaining_time":0.5887773336},
{"learn":[2.255362269],"iteration":204,"passed_time":0.1512208519,"remaining_time":0.5864418402},
{"learn":[2.252525667],"iteration":205,"passed_time":0.1515595964,"remaining_time":0.5841665999},
{"learn":[2.249148513],"iteration":206,"passed_time":0.1518892523,"remaining_time":0.5818752514},
{"learn":[2.248422979],"iteration":207,"passed_time":0.1522211342,"remaining_time":0.5796112418},
{"learn":[2.246256564],"iteration":208,"passed_time":0.1525513597,"remaining_time":0.5773594522},
{"learn":[2.245440105],"iteration":209,"passed_time":0.1528792969,"remaining_time":0.5751173552},
{"learn":[2.244994559],"iteration":210,"passed_time":0.1532365649,"remaining_time":0.5730030791},
{"learn":[2.242606422],"iteration":211,"passed_time":0.1536052091,"remaining_time":0.570947664},
{"learn":[2.239629895],"iteration":212,"passed_time":0.1539901441,"remaining_time":0.568968279},
{"learn":[2.237022226],"iteration":213,"passed_time":0.1543576783,"remaining_time":0.566939884},
{"learn":[2.2344621],"iteration":214,"passed_time":0.1548024037,"remaining_time":0.5652087762},
{"learn":[2.232230741],"iteration":215,"passed_time":0.1552275763,"remaining_time":0.5634186103},
{"learn":[2.229884012],"iteration":216,"passed_time":0.1556837834,"remaining_time":0.5617530063},
{"learn":[2.229115475],"iteration":217,"passed_time":0.1560993912,"remaining_time":0.5599528618},
{"learn":[2.226852296],"iteration":218,"passed_time":0.1565249444,"remaining_time":0.5582008291},
{"learn":[2.226448956],"iteration":219,"passed_time":0.1568956791,"remaining_time":0.5562664986},
{"learn":[2.22618264],"iteration":220,"passed_time":0.1572610572,"remaining_time":0.554327437},
{"learn":[2.22464262],"iteration":221,"passed_time":0.1576094714,"remaining_time":0.5523431026},
{"learn":[2.22444733],"iteration":222,"passed_time":0.1579495189,"remaining_time":0.5503442877},
{"learn":[2.224076956],"iteration":223,"passed_time":0.1583677698,"remaining_time":0.5486312024},
{"learn":[2.222318165],"iteration":224,"passed_time":0.1587117886,"remaining_time":0.5466739384},
{"learn":[2.221499593],"iteration":225,"passed_time":0.1590467029,"remaining_time":0.5446997701},
{"learn":[2.221297946],"iteration":226,"passed_time":0.1593669813,"remaining_time":0.542690205},
{"learn":[2.221070149],"iteration":227,"passed_time":0.1597219521,"remaining_time":0.5408129254},
{"learn":[2.220813629],"iteration":228,"passed_time":0.1600745449,"remaining_time":0.5389409352},
{"learn":[2.220473675],"iteration":229,"passed_time":0.1605433942,"remaining_time":0.5374713632},
{"learn":[2.220065594],"iteration":230,"passed_time":0.1609715706,"remaining_time":0.5358750553},
{"learn":[2.218250814],"iteration":231,"passed_time":0.1613907392,"remaining_time":0.5342589989},
{"learn":[2.217417933],"iteration":232,"passed_time":0.1617703425,"remaining_time":0.5325229729},
{"learn":[2.217143297],"iteration":233,"passed_time":0.1621254206,"remaining_time":0.5307182572},
{"learn":[2.214836116],"iteration":234,"passed_time":0.1625271662,"remaining_time":0.5290777965},
{"learn":[2.214432199],"iteration":235,"passed_time":0.1628938058,"remaining_time":0.5273341849},
{"learn":[2.212778476],"iteration":236,"passed_time":0.1632609864,"remaining_time":0.5256039351},
{"learn":[2.212621288],"iteration":237,"passed_time":0.163591426,"remaining_time":0.5237675066},
{"learn":[2.212388036],"iteration":238,"passed_time":0.1639109685,"remaining_time":0.5219089835},
{"learn":[2.210323515],"iteration":239,"passed_time":0.1642433494,"remaining_time":0.5201039397},
{"learn":[2.210169358],"iteration":240,"passed_time":0.164551498,"remaining_time":0.5182348008},
{"learn":[2.208072252],"iteration":241,"passed_time":0.1648812062,"remaining_time":0.5164460922},
{"learn":[2.20559948],"iteration":242,"passed_time":0.1652137308,"remaining_time":0.5146781655},
{"learn":[2.201920687],"iteration":243,"passed_time":0.165536767,"remaining_time":0.512892606},
{"learn":[2.201771034],"iteration":244,"passed_time":0.1659030575,"remaining_time":0.5112522792},
{"learn":[2.201099742],"iteration":245,"passed_time":0.1662377477,"remaining_time":0.5095254545},
{"learn":[2.199575318],"iteration":246,"passed_time":0.1666282759,"remaining_time":0.5079801286},
{"learn":[2.199104767],"iteration":247,"passed_time":0.1670064952,"remaining_time":0.506406792},
{"learn":[2.198549284],"iteration":248,"passed_time":0.1673641698,"remaining_time":0.5047810906},
{"learn":[2.195948763],"iteration":249,"passed_time":0.1677822378,"remaining_time":0.5033467134},
{"learn":[2.195833069],"iteration":250,"passed_time":0.1681705045,"remaining_time":0.5018315054},
{"learn":[2.19551429],"iteration":251,"passed_time":0.168550678,"remaining_time":0.5003012188},
{"learn":[2.195073498],"iteration":252,"passed_time":0.1689763672,"remaining_time":0.4989144123},
{"learn":[2.194675319],"iteration":253,"passed_time":0.1693714177,"remaining_time":0.4974451875},
{"learn":[2.193611515],"iteration":254,"passed_time":0.1697372842,"remaining_time":0.4958991244},
{"learn":[2.191383226],"iteration":255,"passed_time":0.1701252262,"remaining_time":0.4944264386},
{"learn":[2.189207148],"iteration":256,"passed_time":0.1705263893,"remaining_time":0.4930004174},
{"learn":[2.187228908],"iteration":257,"passed_time":0.1709200103,"remaining_time":0.4915606498},
{"learn":[2.186900278],"iteration":258,"passed_time":0.1714582649,"remaining_time":0.4905427577},
{"learn":[2.18670871],"iteration":259,"passed_time":0.1718096085,"remaining_time":0.4889965781},
{"learn":[2.18653842],"iteration":260,"passed_time":0.1721503921,"remaining_time":0.4874296544},
{"learn":[2.186439599],"iteration":261,"passed_time":0.1725597568,"remaining_time":0.4860652692},
{"learn":[2.184751217],"iteration":262,"passed_time":0.1729884462,"remaining_time":0.4847622999},
{"learn":[2.184630471],"iteration":263,"passed_time":0.1734253002,"remaining_time":0.4834887158},
{"learn":[2.184450263],"iteration":264,"passed_time":0.1737821615,"remaining_time":0.48199958},
{"learn":[2.184001847],"iteration":265,"passed_time":0.1741727215,"remaining_time":0.4806119458},
{"learn":[2.183195126],"iteration":266,"passed_time":0.174572224,"remaining_time":0.4792563303},
{"learn":[2.180820015],"iteration":267,"passed_time":0.174964129,"remaining_time":0.4778870986},
{"learn":[2.18057388],"iteration":268,"passed_time":0.1753228194,"remaining_time":0.4764348735},
{"learn":[2.178203995],"iteration":269,"passed_time":0.1756692116,"remaining_time":0.474957498},
{"learn":[2.176180264],"iteration":270,"passed_time":0.1760195128,"remaining_time":0.4734989845},
{"learn":[2.176057043],"iteration":271,"passed_time":0.1763430768,"remaining_time":0.4719770586},
{"learn":[2.173789596],"iteration":272,"passed_time":0.176672894,"remaining_time":0.470480564},
{"learn":[2.171837028],"iteration":273,"passed_time":0.1770037042,"remaining_time":0.4689952163},
{"learn":[2.169823014],"iteration":274,"passed_time":0.1773593687,"remaining_time":0.4675837902},
{"learn":[2.168977093],"iteration":275,"passed_time":0.1776792569,"remaining_time":0.4660861665},
{"learn":[2.166522191],"iteration":276,"passed_time":0.1780658285,"remaining_time":0.4647710974},
{"learn":[2.166098376],"iteration":277,"passed_time":0.1783943167,"remaining_time":0.4633118585},
{"learn":[2.16592041],"iteration":278,"passed_time":0.1787794681,"remaining_time":0.4620071559},
{"learn":[2.162705807],"iteration":279,"passed_time":0.1792398702,"remaining_time":0.4609025235},
{"learn":[2.162590155],"iteration":280,"passed_time":0.1796189617,"remaining_time":0.4595944251},
{"learn":[2.160277503],"iteration":281,"passed_time":0.1800665246,"remaining_time":0.4584672506},
{"learn":[2.15819394],"iteration":282,"passed_time":0.1804698017,"remaining_time":0.4572326778},
{"learn":[2.156213712],"iteration":283,"passed_time":0.18086307,"remaining_time":0.4559787258},
{"learn":[2.155396795],"iteration":284,"passed_time":0.1812377732,"remaining_time":0.454684238},
{"learn":[2.152147471],"iteration":285,"passed_time":0.1815939019,"remaining_time":0.4533498109},
{"learn":[2.149468257],"iteration":286,"passed_time":0.1819337433,"remaining_time":0.4519817385},
{"learn":[2.149212679],"iteration":287,"passed_time":0.1822653488,"remaining_time":0.4506004455},
{"learn":[2.14854431],"iteration":288,"passed_time":0.1825994424,"remaining_time":0.4492325382},
{"learn":[2.146314494],"iteration":289,"passed_time":0.1829515212,"remaining_time":0.4479157934},
{"learn":[2.14450033],"iteration":290,"passed_time":0.1832855114,"remaining_time":0.4465616067},
{"learn":[2.144411033],"iteration":291,"passed_time":0.1836069933,"remaining_time":0.4451840797},
{"learn":[2.144206689],"iteration":292,"passed_time":0.18392924,"remaining_time":0.4438156065},
{"learn":[2.142909024],"iteration":293,"passed_time":0.1843095489,"remaining_time":0.4425936786},
{"learn":[2.142799563],"iteration":294,"passed_time":0.184671507,"remaining_time":0.4413336014},
{"learn":[2.141320918],"iteration":295,"passed_time":0.1850975424,"remaining_time":0.4402319928},
{"learn":[2.141266313],"iteration":296,"passed_time":0.1855085694,"remaining_time":0.4390994083},
{"learn":[2.139829405],"iteration":297,"passed_time":0.1859121802,"remaining_time":0.4379541962},
{"learn":[2.137245806],"iteration":298,"passed_time":0.1863354751,"remaining_time":0.4368600938},
{"learn":[2.135228068],"iteration":299,"passed_time":0.1867023304,"remaining_time":0.4356387709},
{"learn":[2.135021348],"iteration":300,"passed_time":0.1870485609,"remaining_time":0.4343752294},
{"learn":[2.133689265],"iteration":301,"passed_time":0.1874056073,"remaining_time":0.4331427613},
{"learn":[2.133475112],"iteration":302,"passed_time":0.1877514508,"remaining_time":0.4318903009},
{"learn":[2.133352964],"iteration":303,"passed_time":0.1881108134,"remaining_time":0.4306747569},
{"learn":[2.131218567],"iteration":304,"passed_time":0.1885366161,"remaining_time":0.4296162235},
{"learn":[2.129484889],"iteration":305,"passed_time":0.18892251,"remaining_time":0.4284713136},
{"learn":[2.127441987],"iteration":306,"passed_time":0.1892755115,"remaining_time":0.4272570992},
{"learn":[2.125950967],"iteration":307,"passed_time":0.1896370195,"remaining_time":0.4260675893},
{"learn":[2.125637641],"iteration":308,"passed_time":0.1900289043,"remaining_time":0.4249513685},
{"learn":[2.124428177],"iteration":309,"passed_time":0.1903866052,"remaining_time":0.4237637342},
{"learn":[2.121877278],"iteration":310,"passed_time":0.1907674438,"remaining_time":0.4226326971},
{"learn":[2.119685102],"iteration":311,"passed_time":0.1911649696,"remaining_time":0.4215432664},
{"learn":[2.119545369],"iteration":312,"passed_time":0.1915554509,"remaining_time":0.4204427947},
{"learn":[2.118763623],"iteration":313,"passed_time":0.1919505474,"remaining_time":0.4193569283},
{"learn":[2.114716297],"iteration":314,"passed_time":0.1923654685,"remaining_time":0.4183185585},
{"learn":[2.113001741],"iteration":315,"passed_time":0.1927518701,"remaining_time":0.4172224023},
{"learn":[2.111246541],"iteration":316,"passed_time":0.1931572042,"remaining_time":0.4161715157},
{"learn":[2.110257658],"iteration":317,"passed_time":0.1935352014,"remaining_time":0.4150660609},
{"learn":[2.109870549],"iteration":318,"passed_time":0.1939865023,"remaining_time":0.4141216554},
{"learn":[2.108659081],"iteration":319,"passed_time":0.1943915179,"remaining_time":0.4130819755},
{"learn":[2.108028018],"iteration":320,"passed_time":0.1947721884,"remaining_time":0.4119947536},
{"learn":[2.107727533],"iteration":321,"passed_time":0.1951575779,"remaining_time":0.4109218567},
{"learn":[2.10649466],"iteration":322,"passed_time":0.1956018928,"remaining_time":0.4099767226},
{"learn":[2.105444742],"iteration":323,"passed_time":0.1960518284,"remaining_time":0.4090464074},
{"learn":[2.104822925],"iteration":324,"passed_time":0.1965015898,"remaining_time":0.4081186864},
{"learn":[2.104680355],"iteration":325,"passed_time":0.1969384415,"remaining_time":0.4071672073},
{"learn":[2.104501233],"iteration":326,"passed_time":0.1974640667,"remaining_time":0.4064015807},
{"learn":[2.104421074],"iteration":327,"passed_time":0.1978943644,"remaining_time":0.4054421125},
{"learn":[2.101536117],"iteration":328,"passed_time":0.1983457093,"remaining_time":0.4045287871},
{"learn":[2.101436367],"iteration":329,"passed_time":0.1987713195,"remaining_time":0.4035660123},
{"learn":[2.099305664],"iteration":330,"passed_time":0.199157786,"remaining_time":0.402527368},
{"learn":[2.098150239],"iteration":331,"passed_time":0.199586216,"remaining_time":0.4015770852},
{"learn":[2.097801589],"iteration":332,"passed_time":0.2000103519,"remaining_time":0.4006213355},
{"learn":[2.097424298],"iteration":333,"passed_time":0.200384676,"remaining_time":0.3995694439},
{"learn":[2.097086983],"iteration":334,"passed_time":0.2007802017,"remaining_time":0.398563684},
{"learn":[2.096106334],"iteration":335,"passed_time":0.2011828053,"remaining_time":0.3975755439},
{"learn":[2.095582343],"iteration":336,"passed_time":0.2015796168,"remaining_time":0.3965794836},
{"learn":[2.093935681],"iteration":337,"passed_time":0.2020336238,"remaining_time":0.395698991},
{"learn":[2.093270941],"iteration":338,"passed_time":0.2024178278,"remaining_time":0.3946849091},
{"learn":[2.092926577],"iteration":339,"passed_time":0.2027727593,"remaining_time":0.3936177093},
{"learn":[2.091263499],"iteration":340,"passed_time":0.2032188741,"remaining_time":0.3927309032},
{"learn":[2.08891882],"iteration":341,"passed_time":0.203619789,"remaining_time":0.3917597111},
{"learn":[2.088532359],"iteration":342,"passed_time":0.2040418923,"remaining_time":0.3908324293},
{"learn":[2.086913244],"iteration":343,"passed_time":0.204467173,"remaining_time":0.3899141438},
{"learn":[2.085286582],"iteration":344,"passed_time":0.2048869396,"remaining_time":0.3889882476},
{"learn":[2.084831147],"iteration":345,"passed_time":0.2053061375,"remaining_time":0.388064202},
{"learn":[2.084137695],"iteration":346,"passed_time":0.2057184143,"remaining_time":0.3871300418},
{"learn":[2.082749226],"iteration":347,"passed_time":0.206098393,"remaining_time":0.3861383684},
{"learn":[2.079163981],"iteration":348,"passed_time":0.20647012,"remaining_time":0.3851348084},
{"learn":[2.078165569],"iteration":349,"passed_time":0.2068010594,"remaining_time":0.3840591104},
{"learn":[2.076244815],"iteration":350,"passed_time":0.2071252681,"remaining_time":0.3829752107},
{"learn":[2.074618116],"iteration":351,"passed_time":0.2075010446,"remaining_time":0.3819905593},
{"learn":[2.07375713],"iteration":352,"passed_time":0.2078515711,"remaining_time":0.3809630779},
{"learn":[2.073685258],"iteration":353,"passed_time":0.208236031,"remaining_time":0.3800013447},
{"learn":[2.072745448],"iteration":354,"passed_time":0.208616093,"remaining_time":0.3790348731},
{"learn":[2.071572732],"iteration":355,"passed_time":0.2090258768,"remaining_time":0.3781254626},
{"learn":[2.070267059],"iteration":356,"passed_time":0.2094218959,"remaining_time":0.377194059},
{"learn":[2.068837138],"iteration":357,"passed_time":0.2098286506,"remaining_time":0.3762848986},
{"learn":[2.068093886],"iteration":358,"passed_time":0.210189083,"remaining_time":0.3752958279},
{"learn":[2.068027793],"iteration":359,"passed_time":0.2106034053,"remaining_time":0.3744060539},
{"learn":[2.067223177],"iteration":360,"passed_time":0.2110372761,"remaining_time":0.3735535164},
{"learn":[2.066893747],"iteration":361,"passed_time":0.2114537197,"remaining_time":0.3726725778},
{"learn":[2.063666106],"iteration":362,"passed_time":0.2119048017,"remaining_time":0.3718549825},
{"learn":[2.062286625],"iteration":363,"passed_time":0.2122881323,"remaining_time":0.3709210223},
{"learn":[2.062227991],"iteration":364,"passed_time":0.2126174518,"remaining_time":0.3698961148},
{"learn":[2.06170455],"iteration":365,"passed_time":0.2129468534,"remaining_time":0.3688751504},
{"learn":[2.060149849],"iteration":366,"passed_time":0.2133127979,"remaining_time":0.3679209839},
{"learn":[2.059454254],"iteration":367,"passed_time":0.2136570225,"remaining_time":0.3669327125},
{"learn":[2.058534611],"iteration":368,"passed_time":0.2139906191,"remaining_time":0.3659297579},
{"learn":[2.057276828],"iteration":369,"passed_time":0.2143498573,"remaining_time":0.3649740814},
{"learn":[2.05723222],"iteration":370,"passed_time":0.2146601372,"remaining_time":0.3639386154},
{"learn":[2.05625521],"iteration":371,"passed_time":0.2150275265,"remaining_time":0.3630034586},
{"learn":[2.056129623],"iteration":372,"passed_time":0.2154571649,"remaining_time":0.3621759849},
{"learn":[2.054151193],"iteration":373,"passed_time":0.2158730337,"remaining_time":0.3613275912},
{"learn":[2.053098498],"iteration":374,"passed_time":0.2162243851,"remaining_time":0.3603739752},
{"learn":[2.053027276],"iteration":375,"passed_time":0.2165913622,"remaining_time":0.3594494947},
{"learn":[2.051723443],"iteration":376,"passed_time":0.2170076348,"remaining_time":0.3586094336},
{"learn":[2.051692821],"iteration":377,"passed_time":0.2173829902,"remaining_time":0.3577042855},
{"learn":[2.049504869],"iteration":378,"passed_time":0.2177758294,"remaining_time":0.3568305806},
{"learn":[2.049203026],"iteration":379,"passed_time":0.218140066,"remaining_time":0.3559127393},
{"learn":[2.047486583],"iteration":380,"passed_time":0.2184744686,"remaining_time":0.3549493334},
{"learn":[2.045767828],"iteration":381,"passed_time":0.218813821,"remaining_time":0.3539972287},
{"learn":[2.042550052],"iteration":382,"passed_time":0.2191858804,"remaining_time":0.3531010137},
{"learn":[2.042005963],"iteration":383,"passed_time":0.2195528826,"remaining_time":0.3521994159},
{"learn":[2.039797992],"iteration":384,"passed_time":0.2198830235,"remaining_time":0.3512417129},
{"learn":[2.039653475],"iteration":385,"passed_time":0.2202092696,"remaining_time":0.3502810661},
{"learn":[2.037223289],"iteration":386,"passed_time":0.2205835928,"remaining_time":0.3493998511},
{"learn":[2.037054456],"iteration":387,"passed_time":0.2209175244,"remaining_time":0.3484575385},
{"learn":[2.034731429],"iteration":388,"passed_time":0.2213164084,"remaining_time":0.3476203741},
{"learn":[2.034040167],"iteration":389,"passed_time":0.2217292513,"remaining_time":0.3468072904},
{"learn":[2.033591375],"iteration":390,"passed_time":0.2221119483,"remaining_time":0.3459493005},
{"learn":[2.030905558],"iteration":391,"passed_time":0.2224708531,"remaining_time":0.3450568334},
{"learn":[2.03085129],"iteration":392,"passed_time":0.2228416546,"remaining_time":0.3441854564},
{"learn":[2.029018275],"iteration":393,"passed_time":0.223247596,"remaining_time":0.343370668},
{"learn":[2.02741124],"iteration":394,"passed_time":0.2236619871,"remaining_time":0.3425708916},
{"learn":[2.025445877],"iteration":395,"passed_time":0.2240240484,"remaining_time":0.3416932455},
{"learn":[2.023760143],"iteration":396,"passed_time":0.2244677052,"remaining_time":0.3409421315},
{"learn":[2.023420354],"iteration":397,"passed_time":0.2248609867,"remaining_time":0.3401163668},
{"learn":[2.021467931],"iteration":398,"passed_time":0.2252194167,"remaining_time":0.3392402743},
{"learn":[2.020582319],"iteration":399,"passed_time":0.225554223,"remaining_time":0.3383313345},
{"learn":[2.019355105],"iteration":400,"passed_time":0.2259038655,"remaining_time":0.3374474201},
{"learn":[2.01700382],"iteration":401,"passed_time":0.2262497761,"remaining_time":0.3365606123},
{"learn":[2.015611114],"iteration":402,"passed_time":0.2266411575,"remaining_time":0.3357438487},
{"learn":[2.01397869],"iteration":403,"passed_time":0.2270754568,"remaining_time":0.3349925056},
{"learn":[2.011885385],"iteration":404,"passed_time":0.2275094822,"remaining_time":0.3342423257},
{"learn":[2.011619764],"iteration":405,"passed_time":0.2279314277,"remaining_time":0.3334760296},
{"learn":[2.010814515],"iteration":406,"passed_time":0.2283098367,"remaining_time":0.332647993},
{"learn":[2.010027463],"iteration":407,"passed_time":0.2286635425,"remaining_time":0.3317863165},
{"learn":[2.009905527],"iteration":408,"passed_time":0.229030552,"remaining_time":0.3309463478},
{"learn":[2.009711459],"iteration":409,"passed_time":0.2294496631,"remaining_time":0.3301836616},
{"learn":[2.008814959],"iteration":410,"passed_time":0.2298855296,"remaining_time":0.3294466592},
{"learn":[2.008533822],"iteration":411,"passed_time":0.2303220023,"remaining_time":0.3287119839},
{"learn":[2.007718553],"iteration":412,"passed_time":0.2307516764,"remaining_time":0.3279690897},
{"learn":[2.006642322],"iteration":413,"passed_time":0.2311341246,"remaining_time":0.3271608623},
{"learn":[2.006020977],"iteration":414,"passed_time":0.2314915189,"remaining_time":0.32631937},
{"learn":[2.005629457],"iteration":415,"passed_time":0.2318442117,"remaining_time":0.3254736049},
{"learn":[2.005607964],"iteration":416,"passed_time":0.2321579085,"remaining_time":0.324575685},
{"learn":[2.004915456],"iteration":417,"passed_time":0.232496556,"remaining_time":0.3237153004},
{"learn":[2.002892118],"iteration":418,"passed_time":0.2328670579,"remaining_time":0.3229015767},
{"learn":[2.002771565],"iteration":419,"passed_time":0.233261805,"remaining_time":0.322123445},
{"learn":[2.00094171],"iteration":420,"passed_time":0.2336870197,"remaining_time":0.3213890366},
{"learn":[2.000555757],"iteration":421,"passed_time":0.2340522956,"remaining_time":0.3205739973},
{"learn":[1.997830107],"iteration":422,"passed_time":0.2344189719,"remaining_time":0.3197629947},
{"learn":[1.99647436],"iteration":423,"passed_time":0.2347689956,"remaining_time":0.3189314657},
{"learn":[1.996360128],"iteration":424,"passed_time":0.2351088958,"remaining_time":0.3180885061},
{"learn":[1.994815668],"iteration":425,"passed_time":0.2355394883,"remaining_time":0.3173701087},
{"learn":[1.994184005],"iteration":426,"passed_time":0.2359764349,"remaining_time":0.3166615859},
{"learn":[1.994079978],"iteration":427,"passed_time":0.236345253,"remaining_time":0.3158632821},
{"learn":[1.99242528],"iteration":428,"passed_time":0.2367275884,"remaining_time":0.3150849719},
{"learn":[1.991690119],"iteration":429,"passed_time":0.2371335732,"remaining_time":0.3143398528},
{"learn":[1.991263404],"iteration":430,"passed_time":0.2374887059,"remaining_time":0.3135291733},
{"learn":[1.991195449],"iteration":431,"passed_time":0.2378423121,"remaining_time":0.3127185955},
{"learn":[1.990191158],"iteration":432,"passed_time":0.2382032585,"remaining_time":0.3119197404},
{"learn":[1.989366679],"iteration":433,"passed_time":0.2385549995,"remaining_time":0.311110898},
{"learn":[1.987278687],"iteration":434,"passed_time":0.2388896017,"remaining_time":0.3102818965},
{"learn":[1.987061449],"iteration":435,"passed_time":0.2392273976,"remaining_time":0.3094592942},
{"learn":[1.986949242],"iteration":436,"passed_time":0.2396978523,"remaining_time":0.3088098189},
{"learn":[1.986887035],"iteration":437,"passed_time":0.240068279,"remaining_time":0.3080328146},
{"learn":[1.985501758],"iteration":438,"passed_time":0.2404238043,"remaining_time":0.3072386201},
{"learn":[1.983737529],"iteration":439,"passed_time":0.2407885289,"remaining_time":0.3064581277},
{"learn":[1.981637119],"iteration":440,"passed_time":0.2411215627,"remaining_time":0.3056393504},
{"learn":[1.980310462],"iteration":441,"passed_time":0.241483153,"remaining_time":0.3048588221},
{"learn":[1.979120773],"iteration":442,"passed_time":0.241980807,"remaining_time":0.304251263},
{"learn":[1.977416752],"iteration":443,"passed_time":0.24238388,"remaining_time":0.3035257596},
{"learn":[1.977319494],"iteration":444,"passed_time":0.2427665146,"remaining_time":0.3027762149},
{"learn":[1.976725164],"iteration":445,"passed_time":0.2431520649,"remaining_time":0.3020319372},
{"learn":[1.976487992],"iteration":446,"passed_time":0.2435545953,"remaining_time":0.3013102711},
{"learn":[1.975858444],"iteration":447,"passed_time":0.2439685855,"remaining_time":0.30060415},
{"learn":[1.975383389],"iteration":448,"passed_time":0.2443720262,"remaining_time":0.299886384},
{"learn":[1.974728647],"iteration":449,"passed_time":0.2448061632,"remaining_time":0.2992075327},
{"learn":[1.973584968],"iteration":450,"passed_time":0.2452937486,"remaining_time":0.2985948292},
{"learn":[1.97173747],"iteration":451,"passed_time":0.2457982794,"remaining_time":0.2980032236},
{"learn":[1.970669818],"iteration":452,"passed_time":0.2461978284,"remaining_time":0.2972852365},
{"learn":[1.970576852],"iteration":453,"passed_time":0.2465770813,"remaining_time":0.2965442431},
{"learn":[1.970510654],"iteration":454,"passed_time":0.2469088774,"remaining_time":0.295747996},
{"learn":[1.970270387],"iteration":455,"passed_time":0.2472613269,"remaining_time":0.2949784251},
{"learn":[1.969529492],"iteration":456,"passed_time":0.2475876971,"remaining_time":0.2941796926},
{"learn":[1.96946594],"iteration":457,"passed_time":0.247935243,"remaining_time":0.2934080823},
{"learn":[1.967581317],"iteration":458,"passed_time":0.2483593284,"remaining_time":0.2927285331},
{"learn":[1.966815422],"iteration":459,"passed_time":0.2487383762,"remaining_time":0.2919972242},
{"learn":[1.964272599],"iteration":460,"passed_time":0.2491542874,"remaining_time":0.2913105443},
{"learn":[1.964233264],"iteration":461,"passed_time":0.2496036794,"remaining_time":0.290664025},
{"learn":[1.963992784],"iteration":462,"passed_time":0.2499887402,"remaining_time":0.289943744},
{"learn":[1.963022856],"iteration":463,"passed_time":0.2503338343,"remaining_time":0.2891787396},
{"learn":[1.961748409],"iteration":464,"passed_time":0.2506930368,"remaining_time":0.2884317735},
{"learn":[1.961023825],"iteration":465,"passed_time":0.2510454127,"remaining_time":0.2876786489},
{"learn":[1.960431196],"iteration":466,"passed_time":0.2514195903,"remaining_time":0.2869521234},
{"learn":[1.959934774],"iteration":467,"passed_time":0.2518591645,"remaining_time":0.2863014434},
{"learn":[1.95748214],"iteration":468,"passed_time":0.2522782797,"remaining_time":0.2856285001},
{"learn":[1.955935118],"iteration":469,"passed_time":0.2526221301,"remaining_time":0.2848717637},
{"learn":[1.954953351],"iteration":470,"passed_time":0.2529782803,"remaining_time":0.2841305951},
{"learn":[1.953742414],"iteration":471,"passed_time":0.2533493111,"remaining_time":0.2834077039},
{"learn":[1.95359477],"iteration":472,"passed_time":0.2536700109,"remaining_time":0.2826302236},
{"learn":[1.953516818],"iteration":473,"passed_time":0.2540134688,"remaining_time":0.2818799253},
{"learn":[1.953443007],"iteration":474,"passed_time":0.2544244771,"remaining_time":0.281206001},
{"learn":[1.953317284],"iteration":475,"passed_time":0.2548595932,"remaining_time":0.2805597203},
{"learn":[1.952281438],"iteration":476,"passed_time":0.2552032195,"remaining_time":0.2798140122},
{"learn":[1.950821],"iteration":477,"passed_time":0.2556003766,"remaining_time":0.2791284448},
{"learn":[1.949448117],"iteration":478,"passed_time":0.2559859446,"remaining_time":0.2784314763},
{"learn":[1.949307727],"iteration":479,"passed_time":0.256355172,"remaining_time":0.277718103},
{"learn":[1.947706759],"iteration":480,"passed_time":0.2567570931,"remaining_time":0.2770414373},
{"learn":[1.947063128],"iteration":481,"passed_time":0.2572096033,"remaining_time":0.2764202791},
{"learn":[1.94509205],"iteration":482,"passed_time":0.2576587678,"remaining_time":0.275796238},
{"learn":[1.9447981],"iteration":483,"passed_time":0.2581212549,"remaining_time":0.275187123},
{"learn":[1.943410705],"iteration":484,"passed_time":0.2585843584,"remaining_time":0.2745792671},
{"learn":[1.942535226],"iteration":485,"passed_time":0.2589596983,"remaining_time":0.2738791871},
{"learn":[1.942519071],"iteration":486,"passed_time":0.2592722873,"remaining_time":0.2731143396},
{"learn":[1.940008538],"iteration":487,"passed_time":0.2596126254,"remaining_time":0.2723804594},
{"learn":[1.939444967],"iteration":488,"passed_time":0.2599521193,"remaining_time":0.2716473066},
{"learn":[1.9383183],"iteration":489,"passed_time":0.2603203954,"remaining_time":0.2709457177},
{"learn":[1.938023708],"iteration":490,"passed_time":0.2606965583,"remaining_time":0.2702536623},
{"learn":[1.937890818],"iteration":491,"passed_time":0.2611062274,"remaining_time":0.2695974869},
{"learn":[1.93552809],"iteration":492,"passed_time":0.2615031984,"remaining_time":0.2689292527},
{"learn":[1.93507171],"iteration":493,"passed_time":0.2619244761,"remaining_time":0.268287014},
{"learn":[1.934389042],"iteration":494,"passed_time":0.2623626748,"remaining_time":0.2676629309},
{"learn":[1.933691884],"iteration":495,"passed_time":0.2628171849,"remaining_time":0.2670561717},
{"learn":[1.933512622],"iteration":496,"passed_time":0.2631968058,"remaining_time":0.266374232},
{"learn":[1.933034424],"iteration":497,"passed_time":0.2635502097,"remaining_time":0.2656670789},
{"learn":[1.93178478],"iteration":498,"passed_time":0.2639647461,"remaining_time":0.265022721},
{"learn":[1.930161051],"iteration":499,"passed_time":0.2643545358,"remaining_time":0.2643545358},
{"learn":[1.928682541],"iteration":500,"passed_time":0.2647313732,"remaining_time":0.2636745613},
{"learn":[1.927830822],"iteration":501,"passed_time":0.265079834,"remaining_time":0.2629676441},
{"learn":[1.927073758],"iteration":502,"passed_time":0.2654177016,"remaining_time":0.2622516853},
{"learn":[1.926951015],"iteration":503,"passed_time":0.2657481556,"remaining_time":0.2615299309},
{"learn":[1.926929632],"iteration":504,"passed_time":0.2660669412,"remaining_time":0.2607982889},
{"learn":[1.925566337],"iteration":505,"passed_time":0.2664231219,"remaining_time":0.260104787},
{"learn":[1.925320662],"iteration":506,"passed_time":0.2668083331,"remaining_time":0.2594408446},
{"learn":[1.925241871],"iteration":507,"passed_time":0.2673384195,"remaining_time":0.2589183118},
{"learn":[1.924404372],"iteration":508,"passed_time":0.2677501061,"remaining_time":0.2582815366},
{"learn":[1.923901965],"iteration":509,"passed_time":0.2681297354,"remaining_time":0.2576148438},
{"learn":[1.92221489],"iteration":510,"passed_time":0.2685684809,"remaining_time":0.2570058457},
{"learn":[1.922099404],"iteration":511,"passed_time":0.2689203209,"remaining_time":0.2563146808},
{"learn":[1.921018499],"iteration":512,"passed_time":0.26937529,"remaining_time":0.2557227412},
{"learn":[1.920082805],"iteration":513,"passed_time":0.2697444582,"remaining_time":0.2550502075},
{"learn":[1.918989426],"iteration":514,"passed_time":0.270158261,"remaining_time":0.2544208865},
{"learn":[1.918868795],"iteration":515,"passed_time":0.270564618,"remaining_time":0.2537854169},
{"learn":[1.917317054],"iteration":516,"passed_time":0.2709347419,"remaining_time":0.2531169833},
{"learn":[1.917267212],"iteration":517,"passed_time":0.2712695894,"remaining_time":0.2524168766},
{"learn":[1.916109225],"iteration":518,"passed_time":0.271621259,"remaining_time":0.251733768},
{"learn":[1.915963128],"iteration":519,"passed_time":0.271954024,"remaining_time":0.2510344837},
{"learn":[1.915085368],"iteration":520,"passed_time":0.2722852287,"remaining_time":0.2503351719},
{"learn":[1.914050227],"iteration":521,"passed_time":0.272633126,"remaining_time":0.2496525559},
{"learn":[1.912855201],"iteration":522,"passed_time":0.2730704371,"remaining_time":0.2490527695},
{"learn":[1.911544481],"iteration":523,"passed_time":0.2734859217,"remaining_time":0.2484337762},
{"learn":[1.911436245],"iteration":524,"passed_time":0.2738815094,"remaining_time":0.2477975561},
{"learn":[1.910934136],"iteration":525,"passed_time":0.2742643897,"remaining_time":0.2471507998},
{"learn":[1.910276636],"iteration":526,"passed_time":0.2746473242,"remaining_time":0.2465050937},
{"learn":[1.910200801],"iteration":527,"passed_time":0.2750439432,"remaining_time":0.2458726159},
{"learn":[1.908786259],"iteration":528,"passed_time":0.2754610445,"remaining_time":0.2452592664},
{"learn":[1.908592175],"iteration":529,"passed_time":0.2758325375,"remaining_time":0.2446062125},
{"learn":[1.908562763],"iteration":530,"passed_time":0.2761934756,"remaining_time":0.2439448965},
{"learn":[1.907861674],"iteration":531,"passed_time":0.2765859888,"remaining_time":0.2433124864},
{"learn":[1.906157226],"iteration":532,"passed_time":0.2769608209,"remaining_time":0.2426654847},
{"learn":[1.90571689],"iteration":533,"passed_time":0.2773023438,"remaining_time":0.2419904349},
{"learn":[1.904900529],"iteration":534,"passed_time":0.2776509271,"remaining_time":0.2413227684},
{"learn":[1.904466393],"iteration":535,"passed_time":0.2779659721,"remaining_time":0.2406272594},
{"learn":[1.903660213],"iteration":536,"passed_time":0.2782978068,"remaining_time":0.2399476435},
{"learn":[1.902974329],"iteration":537,"passed_time":0.2786419012,"remaining_time":0.2392798482},
{"learn":[1.902926164],"iteration":538,"passed_time":0.2789615479,"remaining_time":0.2385923443},
{"learn":[1.90087333],"iteration":539,"passed_time":0.2794328531,"remaining_time":0.2380353934},
{"learn":[1.899357032],"iteration":540,"passed_time":0.2799908352,"remaining_time":0.2375522983},
{"learn":[1.897698117],"iteration":541,"passed_time":0.2804035145,"remaining_time":0.2369461433},
{"learn":[1.896045084],"iteration":542,"passed_time":0.2808205859,"remaining_time":0.2363443974},
{"learn":[1.894468122],"iteration":543,"passed_time":0.2812768724,"remaining_time":0.2357762019},
{"learn":[1.894441171],"iteration":544,"passed_time":0.2816312716,"remaining_time":0.2351233552},
{"learn":[1.893339408],"iteration":545,"passed_time":0.2820121655,"remaining_time":0.2344936321},
{"learn":[1.893216651],"iteration":546,"passed_time":0.2823812427,"remaining_time":0.2338550328},
{"learn":[1.892849764],"iteration":547,"passed_time":0.2827683772,"remaining_time":0.2332323111},
{"learn":[1.89207294],"iteration":548,"passed_time":0.2831218615,"remaining_time":0.2325828043},
{"learn":[1.890830359],"iteration":549,"passed_time":0.2834656048,"remaining_time":0.231926404},
{"learn":[1.889364605],"iteration":550,"passed_time":0.2838101364,"remaining_time":0.2312717808},
{"learn":[1.888771954],"iteration":551,"passed_time":0.284132611,"remaining_time":0.23060038},
{"learn":[1.888474352],"iteration":552,"passed_time":0.2844672142,"remaining_time":0.2299400447},
{"learn":[1.887760749],"iteration":553,"passed_time":0.2848068772,"remaining_time":0.2292849589},
{"learn":[1.886362337],"iteration":554,"passed_time":0.2851542829,"remaining_time":0.2286372178},
{"learn":[1.884944868],"iteration":555,"passed_time":0.2855499243,"remaining_time":0.2280290762},
{"learn":[1.884537718],"iteration":556,"passed_time":0.2860028868,"remaining_time":0.227467287},
{"learn":[1.88366265],"iteration":557,"passed_time":0.2864191893,"remaining_time":0.2268768489},
{"learn":[1.882425266],"iteration":558,"passed_time":0.2868372656,"remaining_time":0.2262884332},
{"learn":[1.882415219],"iteration":559,"passed_time":0.2873305078,"remaining_time":0.2257596847},
{"learn":[1.881639021],"iteration":560,"passed_time":0.2877294198,"remaining_time":0.2251572465},
{"learn":[1.881619781],"iteration":561,"passed_time":0.2881310054,"remaining_time":0.2245576163},
{"learn":[1.87924279],"iteration":562,"passed_time":0.2885680808,"remaining_time":0.2239862368},
{"learn":[1.878822509],"iteration":563,"passed_time":0.2890216969,"remaining_time":0.2234281203},
{"learn":[1.876879164],"iteration":564,"passed_time":0.2894190304,"remaining_time":0.2228270411},
{"learn":[1.876754522],"iteration":565,"passed_time":0.2898506851,"remaining_time":0.2222529988},
{"learn":[1.87672851],"iteration":566,"passed_time":0.2902737241,"remaining_time":0.2216728793},
{"learn":[1.875333018],"iteration":567,"passed_time":0.2906757652,"remaining_time":0.2210773426},
{"learn":[1.874201333],"iteration":568,"passed_time":0.2910859001,"remaining_time":0.2204886168},
{"learn":[1.872959347],"iteration":569,"passed_time":0.2915183568,"remaining_time":0.2199173569},
{"learn":[1.872674415],"iteration":570,"passed_time":0.2919893412,"remaining_time":0.2193755295},
{"learn":[1.871418153],"iteration":571,"passed_time":0.2924373445,"remaining_time":0.2188167543},
{"learn":[1.869791873],"iteration":572,"passed_time":0.2928809942,"remaining_time":0.2182551213},
{"learn":[1.869720499],"iteration":573,"passed_time":0.2932902579,"remaining_time":0.2176683796},
{"learn":[1.869459882],"iteration":574,"passed_time":0.2936807832,"remaining_time":0.217068405},
{"learn":[1.868278765],"iteration":575,"passed_time":0.2940709488,"remaining_time":0.2164688928},
{"learn":[1.867449071],"iteration":576,"passed_time":0.2945585297,"remaining_time":0.2159415218},
{"learn":[1.865686901],"iteration":577,"passed_time":0.2950028227,"remaining_time":0.2153826837},
{"learn":[1.86531988],"iteration":578,"passed_time":0.2954172597,"remaining_time":0.2148025325},
{"learn":[1.864662076],"iteration":579,"passed_time":0.2957836865,"remaining_time":0.2141881867},
{"learn":[1.863509569],"iteration":580,"passed_time":0.2961240949,"remaining_time":0.2135559308},
{"learn":[1.862965571],"iteration":581,"passed_time":0.2965094369,"remaining_time":0.2129569495},
{"learn":[1.862232736],"iteration":582,"passed_time":0.2968399031,"remaining_time":0.2123194504},
{"learn":[1.860838413],"iteration":583,"passed_time":0.2972105768,"remaining_time":0.2117116437},
{"learn":[1.858659331],"iteration":584,"passed_time":0.2975439371,"remaining_time":0.2110781776},
{"learn":[1.857415285],"iteration":585,"passed_time":0.2979752237,"remaining_time":0.2105149191},
{"learn":[1.855661232],"iteration":586,"passed_time":0.2984137589,"remaining_time":0.2099572103},
{"learn":[1.854770098],"iteration":587,"passed_time":0.2988615198,"remaining_time":0.209406371},
{"learn":[1.853729928],"iteration":588,"passed_time":0.2992807856,"remaining_time":0.2088359981},
{"learn":[1.851627303],"iteration":589,"passed_time":0.2997250351,"remaining_time":0.208283499},
{"learn":[1.851543907],"iteration":590,"passed_time":0.3001618091,"remaining_time":0.2077261927},
{"learn":[1.850732017],"iteration":591,"passed_time":0.3006050425,"remaining_time":0.2071737455},
{"learn":[1.849927203],"iteration":592,"passed_time":0.3010235322,"remaining_time":0.206604684},
{"learn":[1.849273766],"iteration":593,"passed_time":0.301438193,"remaining_time":0.2060335124},
{"learn":[1.849086051],"iteration":594,"passed_time":0.3018293654,"remaining_time":0.2054468789},
{"learn":[1.848555433],"iteration":595,"passed_time":0.3022213192,"remaining_time":0.2048614312},
{"learn":[1.84773458],"iteration":596,"passed_time":0.3025985893,"remaining_time":0.2042667194},
{"learn":[1.84723242],"iteration":597,"passed_time":0.3029441142,"remaining_time":0.2036513945},
{"learn":[1.846926362],"iteration":598,"passed_time":0.303278381,"remaining_time":0.2030294337},
{"learn":[1.845917473],"iteration":599,"passed_time":0.3036124875,"remaining_time":0.202408325},
{"learn":[1.84432496],"iteration":600,"passed_time":0.303958248,"remaining_time":0.2017959084},
{"learn":[1.844083011],"iteration":601,"passed_time":0.3043547644,"remaining_time":0.201217934},
{"learn":[1.841689993],"iteration":602,"passed_time":0.3047918058,"remaining_time":0.200667242},
{"learn":[1.840835941],"iteration":603,"passed_time":0.3052102801,"remaining_time":0.2001047532},
{"learn":[1.840651459],"iteration":604,"passed_time":0.3055882699,"remaining_time":0.1995163085},
{"learn":[1.839754399],"iteration":605,"passed_time":0.3059829762,"remaining_time":0.1989394267},
{"learn":[1.838859863],"iteration":606,"passed_time":0.3064036522,"remaining_time":0.1983799593},
{"learn":[1.838125144],"iteration":607,"passed_time":0.3068202906,"remaining_time":0.1978183452},
{"learn":[1.837659638],"iteration":608,"passed_time":0.3072407943,"remaining_time":0.1972596889},
{"learn":[1.836114464],"iteration":609,"passed_time":0.3077528334,"remaining_time":0.1967600083},
{"learn":[1.834045923],"iteration":610,"passed_time":0.3081213407,"remaining_time":0.196168906},
{"learn":[1.833557859],"iteration":611,"passed_time":0.3084931285,"remaining_time":0.1955806109},
{"learn":[1.83327051],"iteration":612,"passed_time":0.3088330281,"remaining_time":0.1949728905},
{"learn":[1.831982156],"iteration":613,"passed_time":0.3091895615,"remaining_time":0.1943764996},
{"learn":[1.831344013],"iteration":614,"passed_time":0.3095300117,"remaining_time":0.1937708204},
{"learn":[1.831050733],"iteration":615,"passed_time":0.3098663424,"remaining_time":0.1931634342},
{"learn":[1.829369275],"iteration":616,"passed_time":0.3102072138,"remaining_time":0.1925597454},
{"learn":[1.829197686],"iteration":617,"passed_time":0.3106223976,"remaining_time":0.1920028412},
{"learn":[1.828661872],"iteration":618,"passed_time":0.3110388843,"remaining_time":0.1914471969},
{"learn":[1.827524242],"iteration":619,"passed_time":0.3114668369,"remaining_time":0.1908990291},
{"learn":[1.827283962],"iteration":620,"passed_time":0.3118950169,"remaining_time":0.1903513871},
{"learn":[1.825869396],"iteration":621,"passed_time":0.3123453633,"remaining_time":0.1898176002},
{"learn":[1.825169063],"iteration":622,"passed_time":0.3127684731,"remaining_time":0.1892675993},
{"learn":[1.824245364],"iteration":623,"passed_time":0.3131731106,"remaining_time":0.1887068744},
{"learn":[1.823981665],"iteration":624,"passed_time":0.3135326295,"remaining_time":0.1881195777},
{"learn":[1.823014015],"iteration":625,"passed_time":0.3138843004,"remaining_time":0.18752832},
{"learn":[1.821675927],"iteration":626,"passed_time":0.3142348112,"remaining_time":0.1869371365},
{"learn":[1.820911357],"iteration":627,"passed_time":0.3145859424,"remaining_time":0.1863470869},
{"learn":[1.819737157],"iteration":628,"passed_time":0.3149248441,"remaining_time":0.1857505837},
{"learn":[1.818992847],"iteration":629,"passed_time":0.3152805009,"remaining_time":0.1851647386},
{"learn":[1.818935813],"iteration":630,"passed_time":0.3156549421,"remaining_time":0.184590608},
{"learn":[1.818022989],"iteration":631,"passed_time":0.3160288191,"remaining_time":0.1840167807},
{"learn":[1.81549421],"iteration":632,"passed_time":0.3163957113,"remaining_time":0.1834395356},
{"learn":[1.814173537],"iteration":633,"passed_time":0.316822624,"remaining_time":0.1828976031},
{"learn":[1.813669845],"iteration":634,"passed_time":0.317265744,"remaining_time":0.1823653489},
{"learn":[1.812817259],"iteration":635,"passed_time":0.3176860454,"remaining_time":0.1818203153},
{"learn":[1.812426262],"iteration":636,"passed_time":0.318081338,"remaining_time":0.1812614218},
{"learn":[1.811448969],"iteration":637,"passed_time":0.3185163516,"remaining_time":0.1807255788},
{"learn":[1.811220264],"iteration":638,"passed_time":0.318935755,"remaining_time":0.1801812325},
{"learn":[1.809374797],"iteration":639,"passed_time":0.3193947957,"remaining_time":0.1796595726},
{"learn":[1.809229962],"iteration":640,"passed_time":0.3197442479,"remaining_time":0.1790767317},
{"learn":[1.809211546],"iteration":641,"passed_time":0.3200645723,"remaining_time":0.1784783752},
{"learn":[1.808916361],"iteration":642,"passed_time":0.3204130353,"remaining_time":0.1778965064},
{"learn":[1.807988576],"iteration":643,"passed_time":0.3207558419,"remaining_time":0.1773122356},
{"learn":[1.807898353],"iteration":644,"passed_time":0.3210829051,"remaining_time":0.1767200485},
{"learn":[1.807678652],"iteration":645,"passed_time":0.3214177272,"remaining_time":0.1761329341},
{"learn":[1.807185526],"iteration":646,"passed_time":0.3217427067,"remaining_time":0.1755412294},
{"learn":[1.80695793],"iteration":647,"passed_time":0.3220780865,"remaining_time":0.1749559976},
{"learn":[1.806644594],"iteration":648,"passed_time":0.3224136116,"remaining_time":0.1743716143},
{"learn":[1.806553861],"iteration":649,"passed_time":0.3227324495,"remaining_time":0.1737790113},
{"learn":[1.806479628],"iteration":650,"passed_time":0.3231535524,"remaining_time":0.1732420734},
{"learn":[1.805965276],"iteration":651,"passed_time":0.3235498033,"remaining_time":0.1726922263},
{"learn":[1.805857732],"iteration":652,"passed_time":0.3239763884,"remaining_time":0.172158969},
{"learn":[1.804508269],"iteration":653,"passed_time":0.3243990273,"remaining_time":0.1716239502},
{"learn":[1.804292123],"iteration":654,"passed_time":0.3248704415,"remaining_time":0.1711149654},
{"learn":[1.803574181],"iteration":655,"passed_time":0.3252762578,"remaining_time":0.1705716962},
{"learn":[1.802761735],"iteration":656,"passed_time":0.3256415591,"remaining_time":0.1700076937},
{"learn":[1.80274967],"iteration":657,"passed_time":0.3259542953,"remaining_time":0.1694169742},
{"learn":[1.801855834],"iteration":658,"passed_time":0.3262825972,"remaining_time":0.1688351527},
{"learn":[1.800843741],"iteration":659,"passed_time":0.3266211347,"remaining_time":0.1682593724},
{"learn":[1.799556238],"iteration":660,"passed_time":0.3269545851,"remaining_time":0.167681701},
{"learn":[1.798836637],"iteration":661,"passed_time":0.3273477785,"remaining_time":0.1671352706},
{"learn":[1.798657637],"iteration":662,"passed_time":0.3276645198,"remaining_time":0.1665504422},
{"learn":[1.797138001],"iteration":663,"passed_time":0.328011688,"remaining_time":0.165981818},
{"learn":[1.795827236],"iteration":664,"passed_time":0.3283565031,"remaining_time":0.1654126745},
{"learn":[1.794639076],"iteration":665,"passed_time":0.3286930138,"remaining_time":0.16484004},
{"learn":[1.794260769],"iteration":666,"passed_time":0.3290411747,"remaining_time":0.1642739298},
{"learn":[1.793720423],"iteration":667,"passed_time":0.3294083871,"remaining_time":0.1637179409},
{"learn":[1.793511201],"iteration":668,"passed_time":0.3298372759,"remaining_time":0.1631930319},
{"learn":[1.792482777],"iteration":669,"passed_time":0.3303001973,"remaining_time":0.1626851718},
{"learn":[1.791586815],"iteration":670,"passed_time":0.3306993619,"remaining_time":0.1621461849},
{"learn":[1.791539817],"iteration":671,"passed_time":0.3311668331,"remaining_time":0.1616409542},
{"learn":[1.791441519],"iteration":672,"passed_time":0.331523325,"remaining_time":0.1610819127},
{"learn":[1.790580137],"iteration":673,"passed_time":0.3318774911,"remaining_time":0.1605223473},
{"learn":[1.78928001],"iteration":674,"passed_time":0.3322104982,"remaining_time":0.1599532028},
{"learn":[1.789091548],"iteration":675,"passed_time":0.3325339607,"remaining_time":0.1593801824},
{"learn":[1.787616894],"iteration":676,"passed_time":0.3328854712,"remaining_time":0.158821281},
{"learn":[1.787561611],"iteration":677,"passed_time":0.3331958061,"remaining_time":0.158243436},
{"learn":[1.787243604],"iteration":678,"passed_time":0.3335130117,"remaining_time":0.157669627},
{"learn":[1.785983475],"iteration":679,"passed_time":0.3338573786,"remaining_time":0.1571093546},
{"learn":[1.785825614],"iteration":680,"passed_time":0.3341732607,"remaining_time":0.1565363732},
{"learn":[1.785569571],"iteration":681,"passed_time":0.3345021665,"remaining_time":0.1559702184},
{"learn":[1.785522431],"iteration":682,"passed_time":0.334831217,"remaining_time":0.1554048255},
{"learn":[1.784613691],"iteration":683,"passed_time":0.3351525328,"remaining_time":0.1548365502},
{"learn":[1.783962239],"iteration":684,"passed_time":0.335514487,"remaining_time":0.1542876838},
{"learn":[1.783404351],"iteration":685,"passed_time":0.335956045,"remaining_time":0.153775799},
{"learn":[1.783299587],"iteration":686,"passed_time":0.3363701159,"remaining_time":0.1532515957},
{"learn":[1.783290215],"iteration":687,"passed_time":0.3367440999,"remaining_time":0.1527095337},
{"learn":[1.78326222],"iteration":688,"passed_time":0.3371398262,"remaining_time":0.1521777735},
{"learn":[1.783019193],"iteration":689,"passed_time":0.3375499572,"remaining_time":0.1516528793},
{"learn":[1.782131149],"iteration":690,"passed_time":0.3379805732,"remaining_time":0.1511374777},
{"learn":[1.78204136],"iteration":691,"passed_time":0.3384094381,"remaining_time":0.1506215418},
{"learn":[1.782029564],"iteration":692,"passed_time":0.3387821778,"remaining_time":0.1500809936},
{"learn":[1.782024877],"iteration":693,"passed_time":0.3391144388,"remaining_time":0.1495230811},
{"learn":[1.781734037],"iteration":694,"passed_time":0.3394691594,"remaining_time":0.1489756743},
{"learn":[1.781597074],"iteration":695,"passed_time":0.3397971192,"remaining_time":0.1484171325},
{"learn":[1.781589087],"iteration":696,"passed_time":0.3401065829,"remaining_time":0.1478512118},
{"learn":[1.781584172],"iteration":697,"passed_time":0.340423953,"remaining_time":0.1472894467},
{"learn":[1.781400501],"iteration":698,"passed_time":0.3407323453,"remaining_time":0.1467245149},
{"learn":[1.781384636],"iteration":699,"passed_time":0.3410560242,"remaining_time":0.1461668675},
{"learn":[1.781338881],"iteration":700,"passed_time":0.3413599555,"remaining_time":0.1456014646},
{"learn":[1.781322705],"iteration":701,"passed_time":0.3416719302,"remaining_time":0.1450402211},
{"learn":[1.7800323],"iteration":702,"passed_time":0.3421027963,"remaining_time":0.1445299153},
{"learn":[1.779610531],"iteration":703,"passed_time":0.3425394889,"remaining_time":0.1440222851},
{"learn":[1.779310771],"iteration":704,"passed_time":0.3430141566,"remaining_time":0.1435307464},
{"learn":[1.778376458],"iteration":705,"passed_time":0.3435069134,"remaining_time":0.1430467883},
{"learn":[1.7780283],"iteration":706,"passed_time":0.3439602791,"remaining_time":0.1425464806},
{"learn":[1.777695023],"iteration":707,"passed_time":0.3443247729,"remaining_time":0.1420096521},
{"learn":[1.776696446],"iteration":708,"passed_time":0.3446985843,"remaining_time":0.141477134},
{"learn":[1.77565322],"iteration":709,"passed_time":0.345025119,"remaining_time":0.1409257528},
{"learn":[1.775179296],"iteration":710,"passed_time":0.3453721438,"remaining_time":0.1403833327},
{"learn":[1.77514108],"iteration":711,"passed_time":0.3457005572,"remaining_time":0.1398339332},
{"learn":[1.775122726],"iteration":712,"passed_time":0.3460298771,"remaining_time":0.1392855185},
{"learn":[1.774904919],"iteration":713,"passed_time":0.3463633262,"remaining_time":0.1387393716},
{"learn":[1.773835325],"iteration":714,"passed_time":0.346688993,"remaining_time":0.1381907175},
{"learn":[1.773641939],"iteration":715,"passed_time":0.3470143923,"remaining_time":0.1376425802},
{"learn":[1.771745646],"iteration":716,"passed_time":0.3473484541,"remaining_time":0.1370984833},
{"learn":[1.770998522],"iteration":717,"passed_time":0.3477069314,"remaining_time":0.1365645608},
{"learn":[1.769998057],"iteration":718,"passed_time":0.3480628646,"remaining_time":0.1360301321},
{"learn":[1.769336491],"iteration":719,"passed_time":0.3485051098,"remaining_time":0.1355297649},
{"learn":[1.768657046],"iteration":720,"passed_time":0.3489648224,"remaining_time":0.1350363183},
{"learn":[1.767968955],"iteration":721,"passed_time":0.3493874713,"remaining_time":0.1345286939},
{"learn":[1.767444053],"iteration":722,"passed_time":0.3497893706,"remaining_time":0.134013355},
{"learn":[1.766194605],"iteration":723,"passed_time":0.3501750771,"remaining_time":0.1334921565},
{"learn":[1.765176109],"iteration":724,"passed_time":0.3505883414,"remaining_time":0.1329817847},
{"learn":[1.764708773],"iteration":725,"passed_time":0.351008452,"remaining_time":0.1324742642},
{"learn":[1.763796748],"iteration":726,"passed_time":0.3514268356,"remaining_time":0.1319663358},
{"learn":[1.762867378],"iteration":727,"passed_time":0.3518114826,"remaining_time":0.1314460485},
{"learn":[1.762451613],"iteration":728,"passed_time":0.3521910277,"remaining_time":0.1309242366},
{"learn":[1.761716786],"iteration":729,"passed_time":0.3525387192,"remaining_time":0.1303910331},
{"learn":[1.76084231],"iteration":730,"passed_time":0.3528679697,"remaining_time":0.1298515511},
{"learn":[1.759844881],"iteration":731,"passed_time":0.3532017364,"remaining_time":0.1293142969},
{"learn":[1.759838732],"iteration":732,"passed_time":0.3535177078,"remaining_time":0.1287711159},
{"learn":[1.759671739],"iteration":733,"passed_time":0.3538477442,"remaining_time":0.1282336512},
{"learn":[1.759104986],"iteration":734,"passed_time":0.3542216373,"remaining_time":0.1277125631},
{"learn":[1.758267023],"iteration":735,"passed_time":0.3546778048,"remaining_time":0.1272213865},
{"learn":[1.757608376],"iteration":736,"passed_time":0.3550949868,"remaining_time":0.1267163929},
{"learn":[1.756675479],"iteration":737,"passed_time":0.3555530326,"remaining_time":0.1262261444},
{"learn":[1.756282545],"iteration":738,"passed_time":0.3559677056,"remaining_time":0.1257206646},
{"learn":[1.755724608],"iteration":739,"passed_time":0.3563606033,"remaining_time":0.1252077795},
{"learn":[1.755698982],"iteration":740,"passed_time":0.3567606073,"remaining_time":0.1246977021},
{"learn":[1.754855791],"iteration":741,"passed_time":0.3571357367,"remaining_time":0.1241792723},
{"learn":[1.754321371],"iteration":742,"passed_time":0.3574902998,"remaining_time":0.1236541145},
{"learn":[1.754216779],"iteration":743,"passed_time":0.3578107991,"remaining_time":0.1231176943},
{"learn":[1.753436805],"iteration":744,"passed_time":0.3581311813,"remaining_time":0.1225818137},
{"learn":[1.752620726],"iteration":745,"passed_time":0.3584566427,"remaining_time":0.1220482403},
{"learn":[1.752052812],"iteration":746,"passed_time":0.3588316448,"remaining_time":0.1215320029},
{"learn":[1.75141223],"iteration":747,"passed_time":0.3591890661,"remaining_time":0.1210102201},
{"learn":[1.750149332],"iteration":748,"passed_time":0.3595553205,"remaining_time":0.1204918364},
{"learn":[1.749786227],"iteration":749,"passed_time":0.3598923388,"remaining_time":0.1199641129},
{"learn":[1.749524361],"iteration":750,"passed_time":0.3602148778,"remaining_time":0.1194320966},
{"learn":[1.748463494],"iteration":751,"passed_time":0.3606019396,"remaining_time":0.1189219162},
{"learn":[1.747932021],"iteration":752,"passed_time":0.361097298,"remaining_time":0.1184475865},
{"learn":[1.747591943],"iteration":753,"passed_time":0.361612782,"remaining_time":0.1179797671},
{"learn":[1.74674551],"iteration":754,"passed_time":0.3620485465,"remaining_time":0.1174859522},
{"learn":[1.746718718],"iteration":755,"passed_time":0.3625042335,"remaining_time":0.1169987209},
{"learn":[1.746218386],"iteration":756,"passed_time":0.3629476877,"remaining_time":0.1165076461},
{"learn":[1.745683884],"iteration":757,"passed_time":0.363381536,"remaining_time":0.1160136302},
{"learn":[1.745576834],"iteration":758,"passed_time":0.3637659108,"remaining_time":0.1155040639},
{"learn":[1.744271423],"iteration":759,"passed_time":0.3642029129,"remaining_time":0.1150114462},
{"learn":[1.743982165],"iteration":760,"passed_time":0.3646467523,"remaining_time":0.1145211219},
{"learn":[1.743581542],"iteration":761,"passed_time":0.3650956255,"remaining_time":0.1140324919},
{"learn":[1.743412891],"iteration":762,"passed_time":0.3654776632,"remaining_time":0.113523206},
{"learn":[1.743255747],"iteration":763,"passed_time":0.365922834,"remaining_time":0.113033755},
{"learn":[1.742538643],"iteration":764,"passed_time":0.3663413572,"remaining_time":0.1125362339},
{"learn":[1.741386614],"iteration":765,"passed_time":0.3667429919,"remaining_time":0.1120337599},
{"learn":[1.740285429],"iteration":766,"passed_time":0.3671717373,"remaining_time":0.1115397846},
{"learn":[1.740062876],"iteration":767,"passed_time":0.3676177842,"remaining_time":0.1110512056},
{"learn":[1.739510664],"iteration":768,"passed_time":0.3680504116,"remaining_time":0.1105587062},
{"learn":[1.739489],"iteration":769,"passed_time":0.368482786,"remaining_time":0.1100662867},
{"learn":[1.738635557],"iteration":770,"passed_time":0.3689152995,"remaining_time":0.1095740643},
{"learn":[1.737305048],"iteration":771,"passed_time":0.3694134177,"remaining_time":0.1091013721},
{"learn":[1.736779829],"iteration":772,"passed_time":0.3698429587,"remaining_time":0.1086084756},
{"learn":[1.736366484],"iteration":773,"passed_time":0.3702635582,"remaining_time":0.108113132},
{"learn":[1.736350851],"iteration":774,"passed_time":0.3706646339,"remaining_time":0.1076123131},
{"learn":[1.735698489],"iteration":775,"passed_time":0.3710805147,"remaining_time":0.1071160248},
{"learn":[1.735666811],"iteration":776,"passed_time":0.3714140165,"remaining_time":0.1065963007},
{"learn":[1.734883689],"iteration":777,"passed_time":0.3718236373,"remaining_time":0.1060987757},
{"learn":[1.733419174],"iteration":778,"passed_time":0.3722101913,"remaining_time":0.1055949323},
{"learn":[1.732755906],"iteration":779,"passed_time":0.3726329188,"remaining_time":0.1051015925},
{"learn":[1.732313379],"iteration":780,"passed_time":0.373057508,"remaining_time":0.1046089555},
{"learn":[1.731251862],"iteration":781,"passed_time":0.3734540196,"remaining_time":0.1041086653},
{"learn":[1.730482759],"iteration":782,"passed_time":0.3739073611,"remaining_time":0.10362439},
{"learn":[1.730246255],"iteration":783,"passed_time":0.3743378591,"remaining_time":0.1031339},
{"learn":[1.729447243],"iteration":784,"passed_time":0.3748030083,"remaining_time":0.1026530532},
{"learn":[1.729061155],"iteration":785,"passed_time":0.375232161,"remaining_time":0.1021624459},
{"learn":[1.729030599],"iteration":786,"passed_time":0.3755744487,"remaining_time":0.1016484849},
{"learn":[1.728955427],"iteration":787,"passed_time":0.3759501166,"remaining_time":0.10114394},
{"learn":[1.728633994],"iteration":788,"passed_time":0.3763079326,"remaining_time":0.1006349478},
{"learn":[1.728522408],"iteration":789,"passed_time":0.3767029494,"remaining_time":0.1001362271},
{"learn":[1.726417054],"iteration":790,"passed_time":0.3771049271,"remaining_time":0.0996396078},
{"learn":[1.726245324],"iteration":791,"passed_time":0.37751286,"remaining_time":0.09914479151},
{"learn":[1.725021119],"iteration":792,"passed_time":0.3778883315,"remaining_time":0.09864172082},
{"learn":[1.724916901],"iteration":793,"passed_time":0.3783043498,"remaining_time":0.09814949125},
{"learn":[1.723214687],"iteration":794,"passed_time":0.3787564431,"remaining_time":0.09766675576},
{"learn":[1.722415792],"iteration":795,"passed_time":0.3791847442,"remaining_time":0.09717799976},
{"learn":[1.721346996],"iteration":796,"passed_time":0.3795890509,"remaining_time":0.09668328399},
{"learn":[1.721116136],"iteration":797,"passed_time":0.3800203053,"remaining_time":0.09619561613},
{"learn":[1.720762732],"iteration":798,"passed_time":0.380476379,"remaining_time":0.09571433313},
{"learn":[1.720348275],"iteration":799,"passed_time":0.3809532812,"remaining_time":0.0952383203},
{"learn":[1.719591224],"iteration":800,"passed_time":0.3813314015,"remaining_time":0.09473776392},
{"learn":[1.718857421],"iteration":801,"passed_time":0.3817503047,"remaining_time":0.09424758145},
{"learn":[1.717957632],"iteration":802,"passed_time":0.3821645501,"remaining_time":0.09375643383},
{"learn":[1.717813312],"iteration":803,"passed_time":0.382643798,"remaining_time":0.0932813239},
{"learn":[1.716615286],"iteration":804,"passed_time":0.383096848,"remaining_time":0.09279985759},
{"learn":[1.714710791],"iteration":805,"passed_time":0.3835065505,"remaining_time":0.09230802829},
{"learn":[1.714012309],"iteration":806,"passed_time":0.3839182513,"remaining_time":0.09181688041},
{"learn":[1.713977013],"iteration":807,"passed_time":0.3843053755,"remaining_time":0.09132008922},
{"learn":[1.71295238],"iteration":808,"passed_time":0.3847803415,"remaining_time":0.09084430807},
{"learn":[1.712541416],"iteration":809,"passed_time":0.3852163484,"remaining_time":0.09035939037},
{"learn":[1.71219857],"iteration":810,"passed_time":0.3856224056,"remaining_time":0.08986761362},
{"learn":[1.711534833],"iteration":811,"passed_time":0.3861453684,"remaining_time":0.08940311485},
{"learn":[1.711308807],"iteration":812,"passed_time":0.3866285318,"remaining_time":0.08892931789},
{"learn":[1.71097608],"iteration":813,"passed_time":0.3870720053,"remaining_time":0.08844642874},
{"learn":[1.710246606],"iteration":814,"passed_time":0.3874952736,"remaining_time":0.08795904984},
{"learn":[1.70846941],"iteration":815,"passed_time":0.3879967836,"remaining_time":0.08748947081},
{"learn":[1.708431949],"iteration":816,"passed_time":0.3884375093,"remaining_time":0.08700619852},
{"learn":[1.707420322],"iteration":817,"passed_time":0.3888664459,"remaining_time":0.08652040728},
{"learn":[1.707028488],"iteration":818,"passed_time":0.3892709256,"remaining_time":0.08602934986},
{"learn":[1.706872119],"iteration":819,"passed_time":0.3896784933,"remaining_time":0.08553918145},
{"learn":[1.705657958],"iteration":820,"passed_time":0.390080643,"remaining_time":0.08504803301},
{"learn":[1.705538041],"iteration":821,"passed_time":0.3904891799,"remaining_time":0.08455848421},
{"learn":[1.705310911],"iteration":822,"passed_time":0.3908620407,"remaining_time":0.08406145955},
{"learn":[1.704692403],"iteration":823,"passed_time":0.3912447223,"remaining_time":0.08356683389},
{"learn":[1.703710539],"iteration":824,"passed_time":0.3915994976,"remaining_time":0.0830665601},
{"learn":[1.702915958],"iteration":825,"passed_time":0.3920154144,"remaining_time":0.08257951828},
{"learn":[1.702315813],"iteration":826,"passed_time":0.3924610919,"remaining_time":0.08209887411},
{"learn":[1.701448868],"iteration":827,"passed_time":0.3929018423,"remaining_time":0.08161729091},
{"learn":[1.699975214],"iteration":828,"passed_time":0.3934434632,"remaining_time":0.08115661304},
{"learn":[1.699656982],"iteration":829,"passed_time":0.3939136748,"remaining_time":0.08068111412},
{"learn":[1.699162066],"iteration":830,"passed_time":0.394370582,"remaining_time":0.08020292222},
{"learn":[1.698528306],"iteration":831,"passed_time":0.3948014397,"remaining_time":0.07971952149},
{"learn":[1.697061655],"iteration":832,"passed_time":0.395250102,"remaining_time":0.07923981638},
{"learn":[1.695696759],"iteration":833,"passed_time":0.3956431862,"remaining_time":0.07874912339},
{"learn":[1.695582446],"iteration":834,"passed_time":0.3960360131,"remaining_time":0.07825861337},
{"learn":[1.694714823],"iteration":835,"passed_time":0.396460908,"remaining_time":0.07777462789},
{"learn":[1.693470867],"iteration":836,"passed_time":0.3968957773,"remaining_time":0.07729272604},
{"learn":[1.693203458],"iteration":837,"passed_time":0.397281561,"remaining_time":0.07680144735},
{"learn":[1.693074652],"iteration":838,"passed_time":0.3977144484,"remaining_time":0.07631945911},
{"learn":[1.692057612],"iteration":839,"passed_time":0.3982864412,"remaining_time":0.07586408404},
{"learn":[1.691945726],"iteration":840,"passed_time":0.398814658,"remaining_time":0.07540015533},
{"learn":[1.691745982],"iteration":841,"passed_time":0.3993174494,"remaining_time":0.07493130285},
{"learn":[1.691238061],"iteration":842,"passed_time":0.3997761889,"remaining_time":0.07445416567},
{"learn":[1.690810348],"iteration":843,"passed_time":0.4002984918,"remaining_time":0.07398882075},
{"learn":[1.689978148],"iteration":844,"passed_time":0.40075725,"remaining_time":0.0735116849},
{"learn":[1.689749663],"iteration":845,"passed_time":0.4011923966,"remaining_time":0.07303029442},
{"learn":[1.68959662],"iteration":846,"passed_time":0.4016554499,"remaining_time":0.07255405411},
{"learn":[1.689362831],"iteration":847,"passed_time":0.4021353054,"remaining_time":0.07208085663},
{"learn":[1.689358366],"iteration":848,"passed_time":0.4025192552,"remaining_time":0.07159058602},
{"learn":[1.689099656],"iteration":849,"passed_time":0.4029390455,"remaining_time":0.07110689039},
{"learn":[1.688855001],"iteration":850,"passed_time":0.403382359,"remaining_time":0.07062746356},
{"learn":[1.687944082],"iteration":851,"passed_time":0.4038860642,"remaining_time":0.0701586121},
{"learn":[1.687764594],"iteration":852,"passed_time":0.4043735986,"remaining_time":0.06968689213},
{"learn":[1.686924554],"iteration":853,"passed_time":0.4049121061,"remaining_time":0.06922384952},
{"learn":[1.686920436],"iteration":854,"passed_time":0.4053734771,"remaining_time":0.06874754876},
{"learn":[1.685884152],"iteration":855,"passed_time":0.4058314291,"remaining_time":0.0682707077},
{"learn":[1.684790977],"iteration":856,"passed_time":0.4063537744,"remaining_time":0.06780465547},
{"learn":[1.684604835],"iteration":857,"passed_time":0.4068728642,"remaining_time":0.06733793324},
{"learn":[1.684327265],"iteration":858,"passed_time":0.4073082549,"remaining_time":0.06685735034},
{"learn":[1.683218401],"iteration":859,"passed_time":0.4077650795,"remaining_time":0.06638036178},
{"learn":[1.68313122],"iteration":860,"passed_time":0.4082061961,"remaining_time":0.06590088415},
{"learn":[1.682940232],"iteration":861,"passed_time":0.4086777042,"remaining_time":0.06542636099},
{"learn":[1.682912942],"iteration":862,"passed_time":0.4090782524,"remaining_time":0.06494058004},
{"learn":[1.682586985],"iteration":863,"passed_time":0.4095206677,"remaining_time":0.06446158658},
{"learn":[1.680697019],"iteration":864,"passed_time":0.4100823797,"remaining_time":0.06400129626},
{"learn":[1.680174296],"iteration":865,"passed_time":0.4106235814,"remaining_time":0.06353759805},
{"learn":[1.679714181],"iteration":866,"passed_time":0.411108925,"remaining_time":0.06306515228},
{"learn":[1.679193665],"iteration":867,"passed_time":0.411587006,"remaining_time":0.06259157235},
{"learn":[1.678787834],"iteration":868,"passed_time":0.412039804,"remaining_time":0.06211417068},
{"learn":[1.678681115],"iteration":869,"passed_time":0.4125285399,"remaining_time":0.06164219562},
{"learn":[1.677817434],"iteration":870,"passed_time":0.4129841638,"remaining_time":0.061165278},
{"learn":[1.677632188],"iteration":871,"passed_time":0.4133885686,"remaining_time":0.06068089081},
{"learn":[1.677528162],"iteration":872,"passed_time":0.4137676768,"remaining_time":0.06019300682},
{"learn":[1.677453075],"iteration":873,"passed_time":0.4142466094,"remaining_time":0.05971976291},
{"learn":[1.676559238],"iteration":874,"passed_time":0.4147081653,"remaining_time":0.05924402362},
{"learn":[1.676044386],"iteration":875,"passed_time":0.415159526,"remaining_time":0.05876687354},
{"learn":[1.675153314],"iteration":876,"passed_time":0.4155637633,"remaining_time":0.05828317319},
{"learn":[1.6750364],"iteration":877,"passed_time":0.415991118,"remaining_time":0.05780286606},
{"learn":[1.674569571],"iteration":878,"passed_time":0.4164383099,"remaining_time":0.05732541013},
{"learn":[1.674555561],"iteration":879,"passed_time":0.4169182516,"remaining_time":0.05685248886},
{"learn":[1.67418194],"iteration":880,"passed_time":0.4174481947,"remaining_time":0.05638630553},
{"learn":[1.673851279],"iteration":881,"passed_time":0.4179842225,"remaining_time":0.05592079167},
{"learn":[1.673628421],"iteration":882,"passed_time":0.4184558476,"remaining_time":0.05544658456},
{"learn":[1.672955931],"iteration":883,"passed_time":0.4189629095,"remaining_time":0.05497703338},
{"learn":[1.672273835],"iteration":884,"passed_time":0.4194010748,"remaining_time":0.05449844474},
{"learn":[1.672234983],"iteration":885,"passed_time":0.4197801055,"remaining_time":0.05401233863},
{"learn":[1.671872639],"iteration":886,"passed_time":0.4202061174,"remaining_time":0.05353245915},
{"learn":[1.671741307],"iteration":887,"passed_time":0.4206577575,"remaining_time":0.05305593337},
{"learn":[1.670682827],"iteration":888,"passed_time":0.4211332639,"remaining_time":0.05258244352},
{"learn":[1.670067882],"iteration":889,"passed_time":0.4216528784,"remaining_time":0.0521144007},
{"learn":[1.669716265],"iteration":890,"passed_time":0.4221196989,"remaining_time":0.05163978359},
{"learn":[1.669699623],"iteration":891,"passed_time":0.422606842,"remaining_time":0.05116764454},
{"learn":[1.668970988],"iteration":892,"passed_time":0.4229994323,"remaining_time":0.05068414251},
{"learn":[1.668792485],"iteration":893,"passed_time":0.4234074501,"remaining_time":0.05020267305},
{"learn":[1.668745788],"iteration":894,"passed_time":0.4238751109,"remaining_time":0.04972836496},
{"learn":[1.6681104],"iteration":895,"passed_time":0.4243781979,"remaining_time":0.04925818369},
{"learn":[1.667859038],"iteration":896,"passed_time":0.4247997824,"remaining_time":0.04877857033},
{"learn":[1.667766586],"iteration":897,"passed_time":0.4252227832,"remaining_time":0.04829924709},
{"learn":[1.667385986],"iteration":898,"passed_time":0.4256802436,"remaining_time":0.04782392059},
{"learn":[1.667185603],"iteration":899,"passed_time":0.4261376967,"remaining_time":0.04734863296},
{"learn":[1.666537815],"iteration":900,"passed_time":0.4267176123,"remaining_time":0.04688684086},
{"learn":[1.665598971],"iteration":901,"passed_time":0.4272171259,"remaining_time":0.04641605138},
{"learn":[1.665575745],"iteration":902,"passed_time":0.4276759436,"remaining_time":0.04594082672},
{"learn":[1.665027572],"iteration":903,"passed_time":0.4281323082,"remaining_time":0.04546537786},
{"learn":[1.664959004],"iteration":904,"passed_time":0.4286383122,"remaining_time":0.04499518194},
{"learn":[1.664772074],"iteration":905,"passed_time":0.4290965139,"remaining_time":0.04451994736},
{"learn":[1.663944865],"iteration":906,"passed_time":0.4296132487,"remaining_time":0.04405075207},
{"learn":[1.66372254],"iteration":907,"passed_time":0.4300735757,"remaining_time":0.04357573674},
{"learn":[1.663150064],"iteration":908,"passed_time":0.4305289318,"remaining_time":0.0431002561},
{"learn":[1.663125184],"iteration":909,"passed_time":0.4310025625,"remaining_time":0.04262662706},
{"learn":[1.662459005],"iteration":910,"passed_time":0.4314328355,"remaining_time":0.04214876219},
{"learn":[1.662450633],"iteration":911,"passed_time":0.4318509259,"remaining_time":0.04166982619},
{"learn":[1.662067142],"iteration":912,"passed_time":0.4322850642,"remaining_time":0.04119255267},
{"learn":[1.661978496],"iteration":913,"passed_time":0.4327392553,"remaining_time":0.04071726035},
{"learn":[1.661718036],"iteration":914,"passed_time":0.4332175113,"remaining_time":0.04024424968},
{"learn":[1.661036372],"iteration":915,"passed_time":0.433727577,"remaining_time":0.03977414461},
{"learn":[1.660473745],"iteration":916,"passed_time":0.4341423265,"remaining_time":0.03929532508},
{"learn":[1.659287139],"iteration":917,"passed_time":0.4345908055,"remaining_time":0.03881965801},
{"learn":[1.658601696],"iteration":918,"passed_time":0.435038605,"remaining_time":0.03834399022},
{"learn":[1.658067302],"iteration":919,"passed_time":0.435507671,"remaining_time":0.03787023226},
{"learn":[1.657430391],"iteration":920,"passed_time":0.4359601352,"remaining_time":0.03739506046},
{"learn":[1.657335608],"iteration":921,"passed_time":0.4364907187,"remaining_time":0.0369265467},
{"learn":[1.656582974],"iteration":922,"passed_time":0.4369983139,"remaining_time":0.03645598068},
{"learn":[1.656482888],"iteration":923,"passed_time":0.4374970268,"remaining_time":0.03598460394},
{"learn":[1.656378541],"iteration":924,"passed_time":0.4379715644,"remaining_time":0.03551120792},
{"learn":[1.655615723],"iteration":925,"passed_time":0.4384714776,"remaining_time":0.03503983731},
{"learn":[1.655493054],"iteration":926,"passed_time":0.4389080551,"remaining_time":0.0345634175},
{"learn":[1.655143032],"iteration":927,"passed_time":0.4393464878,"remaining_time":0.0340872275},
{"learn":[1.654920423],"iteration":928,"passed_time":0.4397735005,"remaining_time":0.033610246},
{"learn":[1.654306642],"iteration":929,"passed_time":0.4402127009,"remaining_time":0.03313428931},
{"learn":[1.653782932],"iteration":930,"passed_time":0.440687764,"remaining_time":0.03266106951},
{"learn":[1.652629887],"iteration":931,"passed_time":0.4411977008,"remaining_time":0.03219039019},
{"learn":[1.652275854],"iteration":932,"passed_time":0.4416353337,"remaining_time":0.03171443447},
{"learn":[1.652125343],"iteration":933,"passed_time":0.4420761176,"remaining_time":0.03123878347},
{"learn":[1.652010445],"iteration":934,"passed_time":0.4425479654,"remaining_time":0.03076536658},
{"learn":[1.650647515],"iteration":935,"passed_time":0.4430714452,"remaining_time":0.03029548343},
{"learn":[1.649948481],"iteration":936,"passed_time":0.4434795851,"remaining_time":0.02981773091},
{"learn":[1.649754216],"iteration":937,"passed_time":0.4438578635,"remaining_time":0.02933815303},
{"learn":[1.649355481],"iteration":938,"passed_time":0.4443578723,"remaining_time":0.02886669884},
{"learn":[1.648763772],"iteration":939,"passed_time":0.4447828253,"remaining_time":0.02839039311},
{"learn":[1.647676095],"iteration":940,"passed_time":0.4451865879,"remaining_time":0.02791286789},
{"learn":[1.647279139],"iteration":941,"passed_time":0.4456429534,"remaining_time":0.02743873811},
{"learn":[1.646403046],"iteration":942,"passed_time":0.4460913707,"remaining_time":0.02696416557},
{"learn":[1.645593286],"iteration":943,"passed_time":0.4465309035,"remaining_time":0.02648912139},
{"learn":[1.644993603],"iteration":944,"passed_time":0.4469847619,"remaining_time":0.02601498614},
{"learn":[1.64438722],"iteration":945,"passed_time":0.4473935643,"remaining_time":0.02553832185},
{"learn":[1.64354428],"iteration":946,"passed_time":0.447816812,"remaining_time":0.02506260933},
{"learn":[1.642300725],"iteration":947,"passed_time":0.448355931,"remaining_time":0.0245933633},
{"learn":[1.641682494],"iteration":948,"passed_time":0.4488424402,"remaining_time":0.02412114273},
{"learn":[1.640493241],"iteration":949,"passed_time":0.4492735129,"remaining_time":0.02364597437},
{"learn":[1.640455986],"iteration":950,"passed_time":0.4497867644,"remaining_time":0.02317513297},
{"learn":[1.64003598],"iteration":951,"passed_time":0.4502363033,"remaining_time":0.02270099008},
{"learn":[1.639917261],"iteration":952,"passed_time":0.450603769,"remaining_time":0.02222285115},
{"learn":[1.639733705],"iteration":953,"passed_time":0.4510189133,"remaining_time":0.0217472432},
{"learn":[1.639165853],"iteration":954,"passed_time":0.4514296072,"remaining_time":0.02127155217},
{"learn":[1.638054071],"iteration":955,"passed_time":0.4519202472,"remaining_time":0.02079967665},
{"learn":[1.637434503],"iteration":956,"passed_time":0.4523787977,"remaining_time":0.02032632006},
{"learn":[1.637137724],"iteration":957,"passed_time":0.4529134589,"remaining_time":0.01985633118},
{"learn":[1.637009208],"iteration":958,"passed_time":0.4534053365,"remaining_time":0.01938437831},
{"learn":[1.636640569],"iteration":959,"passed_time":0.453901381,"remaining_time":0.01891255754},
{"learn":[1.63644916],"iteration":960,"passed_time":0.454322119,"remaining_time":0.01843763022},
{"learn":[1.635808027],"iteration":961,"passed_time":0.4548578459,"remaining_time":0.01796735774},
{"learn":[1.635278663],"iteration":962,"passed_time":0.4553705515,"remaining_time":0.0174960648},
{"learn":[1.634939595],"iteration":963,"passed_time":0.4557942309,"remaining_time":0.01702136132},
{"learn":[1.634827079],"iteration":964,"passed_time":0.4562267811,"remaining_time":0.01654708533},
{"learn":[1.634769448],"iteration":965,"passed_time":0.4566211607,"remaining_time":0.01607155224},
{"learn":[1.634337153],"iteration":966,"passed_time":0.4570071193,"remaining_time":0.01559589962},
{"learn":[1.634058137],"iteration":967,"passed_time":0.4573716723,"remaining_time":0.0151197247},
{"learn":[1.633949275],"iteration":968,"passed_time":0.4577179937,"remaining_time":0.01464319691},
{"learn":[1.633798677],"iteration":969,"passed_time":0.4581360517,"remaining_time":0.01416915624},
{"learn":[1.633632998],"iteration":970,"passed_time":0.4584796005,"remaining_time":0.01369300558},
{"learn":[1.633468322],"iteration":971,"passed_time":0.4588175623,"remaining_time":0.01321696682},
{"learn":[1.633325871],"iteration":972,"passed_time":0.4591531042,"remaining_time":0.01274114472},
{"learn":[1.632733498],"iteration":973,"passed_time":0.4595038319,"remaining_time":0.01226601605},
{"learn":[1.631534503],"iteration":974,"passed_time":0.4598928364,"remaining_time":0.01179212401},
{"learn":[1.630630471],"iteration":975,"passed_time":0.4602425737,"remaining_time":0.01131744034},
{"learn":[1.630227747],"iteration":976,"passed_time":0.4606117072,"remaining_time":0.01084346905},
{"learn":[1.629551516],"iteration":977,"passed_time":0.4610748945,"remaining_time":0.01037182789},
{"learn":[1.629391212],"iteration":978,"passed_time":0.4615790298,"remaining_time":0.009901082356},
{"learn":[1.629345976],"iteration":979,"passed_time":0.4619935177,"remaining_time":0.009428439136},
{"learn":[1.628319942],"iteration":980,"passed_time":0.4624237254,"remaining_time":0.008956218942},
{"learn":[1.627646067],"iteration":981,"passed_time":0.4628165842,"remaining_time":0.00848339971},
{"learn":[1.627257335],"iteration":982,"passed_time":0.4631702144,"remaining_time":0.008010064746},
{"learn":[1.626670872],"iteration":983,"passed_time":0.4635350895,"remaining_time":0.007537155926},
{"learn":[1.62602785],"iteration":984,"passed_time":0.4639020881,"remaining_time":0.007064498804},
{"learn":[1.625184453],"iteration":985,"passed_time":0.4642632001,"remaining_time":0.006591972415},
{"learn":[1.625024923],"iteration":986,"passed_time":0.4646046543,"remaining_time":0.006119412873},
{"learn":[1.62430557],"iteration":987,"passed_time":0.4649616429,"remaining_time":0.005647307403},
{"learn":[1.624270905],"iteration":988,"passed_time":0.4653086137,"remaining_time":0.005175323307},
{"learn":[1.623241456],"iteration":989,"passed_time":0.4656718046,"remaining_time":0.004703755602},
{"learn":[1.622800774],"iteration":990,"passed_time":0.4660259511,"remaining_time":0.00423232448},
{"learn":[1.622285785],"iteration":991,"passed_time":0.4663843426,"remaining_time":0.003761164053},
{"learn":[1.621354604],"iteration":992,"passed_time":0.4667531401,"remaining_time":0.00329030411},
{"learn":[1.621246803],"iteration":993,"passed_time":0.4672623131,"remaining_time":0.00282049686},
{"learn":[1.62028427],"iteration":994,"passed_time":0.4678409561,"remaining_time":0.002350959578},
{"learn":[1.620005724],"iteration":995,"passed_time":0.4682966854,"remaining_time":0.00188070958},
{"learn":[1.619327393],"iteration":996,"passed_time":0.4687078577,"remaining_time":0.001410354637},
{"learn":[1.618809967],"iteration":997,"passed_time":0.4690936989,"remaining_time":0.0009400675328},
{"learn":[1.618636731],"iteration":998,"passed_time":0.469554653,"remaining_time":0.0004700246777},
{"learn":[1.618268143],"iteration":999,"passed_time":0.4699166918,"remaining_time":0}
]}